Workbook

Sheet SBI IS
B1: State Bank Of India
B3: Income Statement (2024-2026)
B4: INR ( Rupees in Crores)
B5: Line Items | C5: 2024 | D5: 2025 | E5: 2026
B7: Interest Earned | C7: 439188.51 | D7: 490312.7 | E7: 514932.59
B8: Interest Expense | C8: 259736.05 | D8: 300943.34 | E8: 315004.81
B9: Net Interest Income | C9: =C7-C8 -> 179452.46 | D9: =D7-D8 -> 189369.36 | E9: =E7-E8 -> 199927.78
B10: Other Income | C10: 155386.39 | D10: 173030.62 | E10: 197710.94
B11: Net Revenue | C11: =C9+C10 -> 334838.86 | D11: =D9+D10 -> 362399.98 | E11: =E9+E10 -> 397638.72
B13: Operating expenses | C13: 235893.84 | D13: 236573.52 | E13: 262650.45
B14: Operating Income | C14: =C11-C13 -> 98945.018 | D14: =D11-D13 -> 125826.46 | E14: =E11-E13 -> 134988.27
B16: Provisions and contingencies (ex-tax) | C16: 7704.98 | D16: 19461.17 | E16: 20960.29
B17: Net Profit Before Taxation | C17: =C14-C16 -> 91240.038 | D17: =D14-D16 -> 106365.29 | E17: =E14-E16 -> 114027.98
B18: Taxation | C18: 23101.78 | D18: 27348.14 | E18: 28859.51
B19: Net Profit After taxation | C19: =C17-C18 -> 68138.258 | D19: =D17-D18 -> 79017.154 | E19: =E17-E18 -> 85168.472
B20: Share in Profit of Associates | C20: 1405.1543 | D20: 1505.4709 | E20: 1497.199
B21: Less: Minority Interest | C21: 2458.7491 | D21: 2961.2882 | E21: 3366.8852
B22: Net Profit | C22: =C19+C20-C21 -> 67084.663 | D22: =D19+D20-D21 -> 77561.336 | E22: =E19+E20-E21 -> 83298.786
B24: Basic EPS | C24: =(C22)/C25 -> 75.168157 | D24: =(D22)/D25 -> 86.907186 | E24: =(E22)/E25 -> 91.160855
B25: Basic Shares | C25: 892.46119 | D25: 892.46171 | E25: 913.75608
B26: Diluted EPS | C26: =(C22)/C27 -> 75.168157 | D26: =(D22)/D27 -> 86.907186 | E26: =(E22)/E27 -> 91.160855
B27: Diluted Shares | C27: 892.46119 | D27: 892.46171 | E27: 913.75608

Sheet SBI BS
B1: State Bank Of India
B3: Balance Sheet (2024-2026)
B4: INR ( Rupees in Crores)
B5: Line Items | C5: 2024 | D5: 2025 | E5: 2026
B7: Capital and Liabilities
B8: Capital | C8: 892.4612 | D8: 892.462 | E8: 923.0618
B9: Reserves & Surplus | C9: 414046.71 | D9: 486144.3 | E9: 595207.81
B10: Minority Interest & Other Equity | C10: 15617.962 | D10: 18025.839 | E10: 18768.282
B12: Deposits | C12: 4966537.5 | D12: 5439898 | E12: 6043097.1
B13: Borrowings | C13: 639609.5 | D13: 610857.24 | E13: 777302.15
B14: Other Liabilities and Provisions | C14: 697074.68 | D14: 758367.48 | E14: 886270.15
B15: Total Capital and Liabilities | C15: =SUM(C8:C14) -> 6733778.8 | D15: =SUM(D8:D14) -> 7314185.3 | E15: =SUM(E8:E14) -> 8321568.6
B17: Assets
B18: Cash and Balances with Reserve Bank of India | C18: 225356.34 | D18: 227485.16 | E18: 268681.74
B19: Balances with Banks and Money at Call & Short Notice | C19: 101215.97 | D19: 130447.79 | E19: 133161.47
B20: Investments | C20: 2110548.2 | D20: 2205601.1 | E20: 2359502.2
B21: Advances | C21: 3784272.7 | D21: 4250830.7 | E21: 4978013.2
B22: Fixed Assets | C22: 44708.177 | D22: 46337.695 | E22: 57152.101
B23: Other Assets | C23: 467677.42 | D23: 453482.86 | E23: 525057.89
B24: Total Assets | C24: =SUM(C17:C23) -> 6733778.8 | D24: =SUM(D17:D23) -> 7314185.3 | E24: =SUM(E17:E23) -> 8321568.6
B26: CET 1 Capital | C26: 333705.96 | D26: 394378.8 | E26: 486848.03
B27: Tier 1 Capital | C27: 384177.36 | D27: 441970.13 | E27: 527992.31
B28: Tier 2 Capital | C28: 75846.02 | D28: 78091.97 | E28: 82087.77
B29: Total Capital (Tier1 + Tier 2) | C29: =C27+C28 -> 460023.38 | D29: =D27+D28 -> 520062.1 | E29: =E27+E28 -> 610080.08
B30: Risk-Weighted Assets | C30: 3222358.3 | D30: 3649286.5 | E30: 3962184.6
B32: Total Employee | C32: 232296 | D32: 236226 | E32: 245131

Sheet SBI CF
B1: State Bank Of India
B3: Cash Flow (2024-2026)
B4: INR ( Rupees in Crores)
B5: Line Items | C5: 2024 | D5: 2025 | E5: 2026
B7: Cash Flow From Operating Activites
B8: Net Profit/(Loss) before taxes (including share in profit from associates and net of minority interest) | C8: ='SBI IS'!C17+'SBI IS'!C20-'SBI IS'!C21 -> 90186.443 | D8: ='SBI IS'!D17+'SBI IS'!D20-'SBI IS'!D21 -> 104909.48 | E8: ='SBI IS'!E17+'SBI IS'!E20-'SBI IS'!E21 -> 112158.3
B9: Depreciation on Fixed Assets | C9: 3849.1245 | D9: 3991.4767 | E9: 4829.7185
B10: Other Operating Activities | C10: 11088.191 | D10: 20360.15 | E10: 28893.687
B11: Tax refund / (Taxes paid) | C11: -31268.268 | D11: -33761.445 | E11: -36322.966
B12: Change in Net Working Capital | C12: -52223.064 | D12: -50015.65 | E12: -71461.347
B14: Total Cash Flow From Operating Activites | C14: =C8+C9+C1+C10+C11+C12 -> 21632.427 | D14: =D8+D9+D1+D10+D11+D12 -> 45484.008 | E14: =E8+E9+E1+E10+E11+E12 -> 38097.388
B16: Cash Flow From Investing Activites
B17: Purchase of Investments | C17: -82.161 | D17: - | E17: -108.2683
B18: Sale Of Investments | C18: - | D18: -6.519 | E18: 7779.4109
B19: Purchase of Fixed Assets | C19: -4175.1262 | D19: -5637.2241 | E19: -8362.9582
B20: Income from Investments in Associates | C20: 5.5719 | D20: 9.0009 | E20: 0.9299
B21: Total Cash Flow From Investing Activites | C21: =SUM(C17:C20) -> -4251.7153 | D21: =SUM(D17:D20) -> -5634.7422 | E21: =SUM(E17:E20) -> -690.8857
B23: Cash Flow From Financing Activites
B24: Dividend paid | C24: -10084.811 | D24: -12226.718 | E24: -14190.146
B25: Other Financing Activities | C25: 188.53 | D25: 1489.9243 | E25: 10763.008
B26: Total Cash Flow From Financing Activites | C26: =SUM(C24:C25) -> -9896.2815 | D26: =SUM(D24:D25) -> -10736.794 | E26: =SUM(E24:E25) -> -3427.1374
B28: Effect of fluctuation in foreign currency translation reserve | C28: 775.9581 | D28: 2248.1669 | E28: 9930.8997
B29: Net Change in Cash | C29: =C14+C21+C26+C28 -> 8260.3878 | D29: =D14+D21+D26+D28 -> 31360.639 | E29: =E14+E21+E26+E28 -> 43910.265
B31: Cash and cash equivalents at the beginning of the year | C31: 318311.91 | D31: ='SBI BS'!C18+'SBI BS'!C19 -> 326572.3 | E31: ='SBI BS'!D18+'SBI BS'!D19 -> 357932.94
B32: Cash and cash equivalents at the end of the year | C32: =C29+C31 -> 326572.3 | D32: =D31+D29 -> 357932.94 | E32: =E31+E29 -> 401843.21

Sheet SBI IS Forecasting
B1: State Bank Of India
B3: Income Statement (2024-2026)
B4: INR ( Rupees in Crores)
B5: Line Items | C5: 2024 | D5: 2025 | E5: 2026 | F5: 2027 | G5: 2028 | H5: 2029
B7: Interest Earned | C7: 439188.51 | D7: 490312.7 | E7: 514932.59 | F7: =E7*(1+$C$31) -> 557831.28 | G7: =F7*(1+$C$31) -> 604303.83 | H7: =G7*(1+$C$31) -> 654647.97
B8: Interest Expense | C8: 259736.05 | D8: 300943.34 | E8: 315004.81 | F8: =E8*(1+$C$32) -> 347351.91 | G8: =F8*(1+$C$32) -> 383020.66 | H8: =G8*(1+$C$32) -> 422352.14
B9: Net Interest Income | C9: =C7-C8 -> 179452.46 | D9: =D7-D8 -> 189369.36 | E9: =E7-E8 -> 199927.78 | F9: =F7-F8 -> 210479.37 | G9: =G7-G8 -> 221283.17 | H9: =H7-H8 -> 232295.83
B10: Other Income | C10: 155386.39 | D10: 173030.62 | E10: 197710.94 | F10: =E10*(1+$C$33) -> 223036.35 | G10: =F10*(1+$C$33) -> 251605.77 | H10: =G10*(1+$C$33) -> 283834.73
B11: Net Revenue | C11: =C9+C10 -> 334838.86 | D11: =D9+D10 -> 362399.98 | E11: =E9+E10 -> 397638.72 | F11: =F9+F10 -> 433515.72 | G11: =G9+G10 -> 472888.93 | H11: =H9+H10 -> 516130.55
B13: Operating expenses | C13: 235893.84 | D13: 236573.52 | E13: 262650.45 | F13: =E13*(1+$C$34) -> 277504.5 | G13: =F13*(1+$C$34) -> 293198.61 | H13: =G13*(1+$C$34) -> 309780.3
B14: Operating Income | C14: =C11-C13 -> 98945.018 | D14: =D11-D13 -> 125826.46 | E14: =E11-E13 -> 134988.27 | F14: =F11-F13 -> 156011.22 | G14: =G11-G13 -> 179690.32 | H14: =H11-H13 -> 206350.26
B16: Provisions and contingencies (ex-tax) | C16: 7704.98 | D16: 19461.17 | E16: 20960.29 | F16: =$C$35*'SBI BS Forecasting'!F21 -> 20605.677 | G16: =$C$35*'SBI BS Forecasting'!G21 -> 23638.39 | H16: =$C$35*'SBI BS Forecasting'!H21 -> 27117.453
B17: Net Profit Before Taxation | C17: =C14-C16 -> 91240.038 | D17: =D14-D16 -> 106365.29 | E17: =E14-E16 -> 114027.98 | F17: =F14-F16 -> 135405.54 | G17: =G14-G16 -> 156051.93 | H17: =H14-H16 -> 179232.81
B18: Taxation | C18: 23101.78 | D18: 27348.14 | E18: 28859.51 | F18: =F17*$C$36 -> 34456.402 | G18: =G17*$C$36 -> 39710.253 | H18: =H17*$C$36 -> 45609.048
B19: Net Profit After taxation | C19: =C17-C18 -> 68138.258 | D19: =D17-D18 -> 79017.154 | E19: =E17-E18 -> 85168.472 | F19: =F17-F18 -> 100949.14 | G19: =G17-G18 -> 116341.68 | H19: =H17-H18 -> 133623.76
B20: Share in Profit of Associates | C20: 1405.1543 | D20: 1505.4709 | E20: 1497.199 | F20: =E20*(1+$C$37) -> 1546.5297 | G20: =F20*(1+$C$37) -> 1597.4858 | H20: =G20*(1+$C$37) -> 1650.1208
B21: Less: Minority Interest | C21: 2458.7491 | D21: 2961.2882 | E21: 3366.8852 | F21: =E21*(1+$C$38) -> 3941.5359 | G21: =F21*(1+$C$38) -> 4614.2665 | H21: =G21*(1+$C$38) -> 5401.8169
B22: Net Profit | C22: =C19+C20-C21 -> 67084.663 | D22: =D19+D20-D21 -> 77561.336 | E22: =E19+E20-E21 -> 83298.786 | F22: =F19+F20-F21 -> 98554.131 | G22: =G19+G20-G21 -> 113324.9 | H22: =H19+H20-H21 -> 129872.06
B24: Basic EPS | C24: =(C22)/C25 -> 75.168157 | D24: =(D22)/D25 -> 86.907186 | E24: =(E22)/E25 -> 91.160855 | F24: =(F22)/F25 -> 106.58446 | G24: =(G22)/G25 -> 121.11384 | H24: =(H22)/H25 -> 137.1619
B25: Basic Shares | C25: 892.46119 | D25: 892.46171 | E25: 913.75608 | F25: =E25*(1+$C$39) -> 924.65757 | G25: =F25*(1+$C$39) -> 935.68913 | H25: =G25*(1+$C$39) -> 946.85229
B26: Diluted EPS | C26: =(C22)/C27 -> 75.168157 | D26: =(D22)/D27 -> 86.907186 | E26: =(E22)/E27 -> 91.160855 | F26: =(F22)/F27 -> 106.58446 | G26: =(G22)/G27 -> 121.11384 | H26: =(H22)/H27 -> 137.1619
B27: Diluted Shares | C27: 892.46119 | D27: 892.46171 | E27: 913.75608 | F27: =F25 -> 924.65757 | G27: =G25 -> 935.68913 | H27: =H25 -> 946.85229
B29: Key Forecast Assumptions (applied 2027-2029)
B30: Driver / Assumption | C30: Value | D30: Basis / Note
B31: Interest Earned growth | C31: =AVERAGE(D7/C7-1,E7/D7-1) -> 0.083309326 | D31: Average YoY growth, FY2024-FY2026
B32: Interest Expense growth | C32: =AVERAGE(D8/C8-1,E8/D8-1) -> 0.10268764 | D32: Average YoY growth, FY2024-FY2026
B33: Other Income growth | C33: =AVERAGE(D10/C10-1,E10/D10-1) -> 0.12809311 | D33: Average YoY growth, FY2024-FY2026
B34: Operating Expenses growth | C34: =AVERAGE(D13/C13-1,E13/D13-1) -> 0.056554445 | D34: Average YoY growth, FY2024-FY2026
B35: Provisions (% of Advances) | C35: =AVERAGE(C16/'SBI BS Forecasting'!C21,D16/'SBI BS Forecasting'!D21,E16/'SBI BS Forecasting'!E21) -> 0.0036082768 | D35: Avg Provisions/Advances FY2024-26; applied to 'SBI BS Forecasting' Advances
B36: Effective Tax Rate | C36: =AVERAGE(C18/C17,D18/D17,E18/E17) -> 0.25446819 | D36: Average effective tax rate (Tax/PBT), FY2024-FY2026
B37: Share in Profit of Associates growth | C37: =AVERAGE(D20/C20-1,E20/D20-1) -> 0.032948658 | D37: Average YoY growth, FY2024-FY2026
B38: Minority Interest growth | C38: =AVERAGE(D21/C21-1,E21/D21-1) -> 0.17067726 | D38: Average YoY growth, FY2024-FY2026
B39: Basic/Diluted Shares growth | C39: =AVERAGE(D25/C25-1,E25/D25-1) -> 0.01193042 | D39: Average YoY growth, FY2024-FY2026

Sheet SBI BS Forecasting
B1: State Bank Of India
B3: Balance Sheet Forecast (2024-2029)
B4: INR ( Rupees in Crores)
B5: Line Items | C5: 2024 | D5: 2025 | E5: 2026 | F5: 2027 | G5: 2028 | H5: 2029
B7: Capital and Liabilities
B8: Capital | C8: 892.4612 | D8: 892.462 | E8: 923.0618 | F8: =E8*(1+$C$31) -> 938.8867 | G8: =F8*(1+$C$31) -> 954.9829 | H8: =G8*(1+$C$31) -> 971.35506
B9: Reserves & Surplus | C9: 414046.71 | D9: 486144.3 | E9: 595207.81 | F9: =E9+'SBI IS Forecasting'!F22+'[1]SBI CF Forecasting'!F24+$C$39 -> 701407.34 | G9: =F9+'[1]SBI IS Forecasting'!G22+'[1]SBI CF Forecasting'!G24+$C$39 -> 820022.59 | H9: =G9+'[1]SBI IS Forecasting'!H22+'[1]SBI CF Forecasting'!H24+$C$39 -> 952546.71
B10: Minority Interest & Other Equity | C10: 15617.962 | D10: 18025.839 | E10: 18768.282 | F10: =E10*(1+$C$32) -> 20601.58 | G10: =F10*(1+$C$32) -> 22613.955 | H10: =G10*(1+$C$32) -> 24822.901
B12: Deposits | C12: 4966537.5 | D12: 5439898 | E12: 6043097.1 | F12: =E12*(1+$C$33) -> 6666123 | G12: =F12*(1+$C$33) -> 7353381.1 | H12: =G12*(1+$C$33) -> 8111493.5
B13: Borrowings | C13: 639609.5 | D13: 610857.24 | E13: 777302.15 | F13: =E13*(1+$C$34) -> 865729.88 | G13: =F13*(1+$C$34) -> 964217.36 | H13: =G13*(1+$C$34) -> 1073909
B14: Other Liabilities and Provisions | C14: 697074.68 | D14: 758367.48 | E14: 886270.15 | F14: =F24-(F8+F9+F10+F12+F13) -> 1023877.4 | G14: =G24-(G8+G9+G10+G12+G13) -> 1199662.2 | H14: =H24-(H8+H9+H10+H12+H13) -> 1421430.9
B15: Total Capital and Liabilities | C15: =SUM(C8:C14) -> 6733778.8 | D15: =SUM(D8:D14) -> 7314185.3 | E15: =SUM(E8:E14) -> 8321568.6 | F15: =SUM(F8:F14) -> 9278678.1 | G15: =SUM(G8:G14) -> 10360852 | H15: =SUM(H8:H14) -> 11585174
B17: Assets
B18: Cash and Balances with Reserve Bank of India | C18: 225356.34 | D18: 227485.16 | E18: 268681.74 | F18: ='[1]SBI CF Forecasting'!F32-F19 -> 300265.95 | G18: ='[1]SBI CF Forecasting'!G32-G19 -> 336142.02 | H18: ='[1]SBI CF Forecasting'!H32-H19 -> 376553.9
B19: Balances with Banks and Money at Call & Short Notice | C19: 101215.97 | D19: 130447.79 | E19: 133161.47 | F19: =E19*(1+$C$35) -> 153775.48 | G19: =F19*(1+$C$35) -> 177580.64 | H19: =G19*(1+$C$35) -> 205070.95
B20: Investments | C20: 2110548.2 | D20: 2205601.1 | E20: 2359502.2 | F20: =E20*(1+$C$36) -> 2494954.6 | G20: =F20*(1+$C$36) -> 2638183 | H20: =G20*(1+$C$36) -> 2789633.8
B21: Advances | C21: 3784272.7 | D21: 4250830.7 | E21: 4978013.2 | F21: =E21*(1+$C$37) -> 5710669.8 | G21: =F21*(1+$C$37) -> 6551157.7 | H21: =G21*(1+$C$37) -> 7515347.3
B22: Fixed Assets | C22: 44708.177 | D22: 46337.695 | E22: 57152.101 | F22: =E22-'[1]SBI CF Forecasting'!F19-'[1]SBI CF Forecasting'!F9 -> 60486.433 | G22: =F22-'[1]SBI CF Forecasting'!G19-'[1]SBI CF Forecasting'!G9 -> 63661.756 | H22: =G22-'[1]SBI CF Forecasting'!H19-'[1]SBI CF Forecasting'!H9 -> 66570.943
B23: Other Assets | C23: 467677.42 | D23: 453482.86 | E23: 525057.89 | F23: =E23*(1+$C$38) -> 558525.82 | G23: =F23*(1+$C$38) -> 594127.05 | H23: =G23*(1+$C$38) -> 631997.56
B24: Total Assets | C24: =SUM(C17:C23) -> 6733778.8 | D24: =SUM(D17:D23) -> 7314185.3 | E24: =SUM(E17:E23) -> 8321568.6 | F24: =SUM(F17:F23) -> 9278678.1 | G24: =SUM(G17:G23) -> 10360852 | H24: =SUM(H17:H23) -> 11585174
B26: Balance Check (Total Assets − Total Capital & Liabilities) | C26: =C24-C15 -> 0 | D26: =D24-D15 -> 9.9998899e-05 | E26: =E24-E15 -> 0 | F26: =F24-F15 -> 0 | G26: =G24-G15 -> 0 | H26: =H24-H15 -> 0
B29: Key Forecast Assumptions (applied 2027-2029)
B30: Driver / Assumption | C30: Value | D30: Basis / Note
B31: Capital growth | C31: =AVERAGE(D8/C8-1,E8/D8-1) -> 0.017143923 | D31: Formula: avg YoY growth, FY2024-FY2026 (row 8)
B32: Minority Interest & Other Equity growth | C32: =AVERAGE(D10/C10-1,E10/D10-1) -> 0.097680633 | D32: Formula: avg YoY growth, FY2024-FY2026 (row 10)
B33: Deposits growth | C33: =AVERAGE(D12/C12-1,E12/D12-1) -> 0.10309712 | D33: Formula: avg YoY growth, FY2024-FY2026 (row 12)
B34: Borrowings growth | C34: =AVERAGE(D13/C13-1,E13/D13-1) -> 0.11376237 | D34: Formula: avg YoY growth, FY2024-FY2026 (row 13)
B35: Balances with Banks & Money at Call growth | C35: =AVERAGE(D19/C19-1,E19/D19-1) -> 0.15480463 | D35: Formula: avg YoY growth, FY2024-FY2026 (row 19)
B36: Investments growth | C36: =AVERAGE(D20/C20-1,E20/D20-1) -> 0.057407218 | D36: Formula: avg YoY growth, FY2024-FY2026 (row 20)
B37: Advances growth | C37: =AVERAGE(D21/C21-1,E21/D21-1) -> 0.14717851 | D37: Formula: avg YoY growth, FY2024-FY2026 (row 21)
B38: Other Assets growth | C38: =AVERAGE(D23/C23-1,E23/D23-1) -> 0.063741422 | D38: Formula: avg YoY growth, FY2024-FY2026 (row 23)
B39: Other Reserve Movements (Rs Cr, flat p.a.) | C39: =AVERAGE((D9-C9)-('SBI IS Forecasting'!D22+'SBI CF Forecasting'!D24),(E9-D9)-('SBI IS Forecasting'!E22+'SBI CF Forecasting'!E24)) -> 23358.92 | D39: Formula: AVERAGE of (actual reserve change less Net Profit less Dividends) for FY2025 and FY2026 - captures OCI/associate equity pickup etc. not modeled elsewhere
B40: Other Liabilities and Provisions | C40: Plug | D40: Balancing item = Total Assets less all other liabilities & equity, so the Balance Sheet ties out exactly each forecast year

Sheet SBI CF Forecasting
B1: State Bank Of India
B3: Cash Flow Forecast (2024-2029)
B4: INR ( Rupees in Crores)
B5: Line Items | C5: 2024 | D5: 2025 | E5: 2026 | F5: 2027 | G5: 2028 | H5: 2029
B7: Cash Flow From Operating Activites
B8: Net Profit/(Loss) before taxes (including share in profit from associates and net of minority interest) | C8: ='[1]SBI IS Forecasting'!C17+'[1]SBI IS Forecasting'!C20-'[1]SBI IS Forecasting'!C21 -> 90186.443 | D8: ='[1]SBI IS Forecasting'!D17+'[1]SBI IS Forecasting'!D20-'[1]SBI IS Forecasting'!D21 -> 104909.48 | E8: ='[1]SBI IS Forecasting'!E17+'[1]SBI IS Forecasting'!E20-'[1]SBI IS Forecasting'!E21 -> 112158.3 | F8: ='SBI IS Forecasting'!F17+'SBI IS Forecasting'!F20-'SBI IS Forecasting'!F21 -> 133010.53 | G8: ='SBI IS Forecasting'!G17+'SBI IS Forecasting'!G20-'SBI IS Forecasting'!G21 -> 153035.15 | H8: ='SBI IS Forecasting'!H17+'SBI IS Forecasting'!H20-'SBI IS Forecasting'!H21 -> 175481.11
B9: Depreciation on Fixed Assets | C9: 3849.1245 | D9: 3991.4767 | E9: 4829.7185 | F9: =E9*(1+$C$37) -> 5426.1669 | G9: =F9*(1+$C$37) -> 6096.2739 | H9: =G9*(1+$C$37) -> 6849.1362
B10: Other Operating Activities | C10: 11088.191 | D10: 20360.15 | E10: 28893.687 | F10: =$C$38*'SBI IS Forecasting'!F11 -> 23404.011 | G10: =$C$38*'SBI IS Forecasting'!G11 -> 25529.635 | H10: =$C$38*'SBI IS Forecasting'!H11 -> 27864.1
B11: Tax refund / (Taxes paid) | C11: -31268.268 | D11: -33761.445 | E11: -36322.966 | F11: =E11*(1+$C$39) -> -39149.006 | G11: =F11*(1+$C$39) -> -42194.921 | H11: =G11*(1+$C$39) -> -45477.818
B12: Change in Net Working Capital | C12: -52223.064 | D12: -50015.65 | E12: -71461.347 | F12: =$C$40*'SBI BS Forecasting'!F21 -> -75992.854 | G12: =$C$40*'SBI BS Forecasting'!G21 -> -87177.369 | H12: =$C$40*'SBI BS Forecasting'!H21 -> -100008
B14: Total Cash Flow From Operating Activites | C14: =C8+C9+C1+C10+C11+C12 -> 21632.427 | D14: =D8+D9+D1+D10+D11+D12 -> 45484.008 | E14: =E8+E9+E1+E10+E11+E12 -> 38097.388 | F14: =SUM(F8:F12) -> 46698.85 | G14: =SUM(G8:G12) -> 55288.769 | H14: =SUM(H8:H12) -> 64708.523
B16: Cash Flow From Investing Activites
B17: Purchase of Investments | C17: -82.161 | D17: - | E17: -108.2683 | F17: =E17*(1+$C$41) -> -114.48368 | G17: =F17*(1+$C$41) -> -121.05587 | H17: =G17*(1+$C$41) -> -128.00535
B18: Sale Of Investments | C18: - | D18: -6.519 | E18: 7779.4109 | F18: =E18*(1+$C$41) -> 8226.0052 | G18: =F18*(1+$C$41) -> 8698.2373 | H18: =G18*(1+$C$41) -> 9197.5789
B19: Purchase of Fixed Assets | C19: -4175.1262 | D19: -5637.2241 | E19: -8362.9582 | F19: =-$C$42*'SBI BS Forecasting'!E22 -> -8760.4981 | G19: =-$C$42*'SBI BS Forecasting'!F22 -> -9271.5975 | H19: =-$C$42*'SBI BS Forecasting'!G22 -> -9758.3235
B20: Income from Investments in Associates | C20: 5.5719 | D20: 9.0009 | E20: 0.9299 | F20: =$C$43 -> 0.9299 | G20: =$C$43 -> 0.9299 | H20: =$C$43 -> 0.9299
B21: Total Cash Flow From Investing Activites | C21: =SUM(C17:C20) -> -4251.7153 | D21: =SUM(D17:D20) -> -5634.7422 | E21: =SUM(E17:E20) -> -690.8857 | F21: =SUM(F17:F20) -> -648.04664 | G21: =SUM(G17:G20) -> -693.48611 | H21: =SUM(H17:H20) -> -687.82002
B23: Cash Flow From Financing Activites
B24: Dividend paid | C24: -10084.811 | D24: -12226.718 | E24: -14190.146 | F24: =-$C$44*'SBI IS Forecasting'!F22 -> -15713.514 | G24: =-$C$44*'SBI IS Forecasting'!G22 -> -18068.572 | H24: =-$C$44*'SBI IS Forecasting'!H22 -> -20706.859
B25: Other Financing Activities | C25: 188.53 | D25: 1489.9243 | E25: 10763.008 | F25: =E25*(1+$C$45) -> 11930.039 | G25: =F25*(1+$C$45) -> 13223.61 | H25: =G25*(1+$C$45) -> 14657.442
B26: Total Cash Flow From Financing Activites | C26: =SUM(C24:C25) -> -9896.2815 | D26: =SUM(D24:D25) -> -10736.794 | E26: =SUM(E24:E25) -> -3427.1374 | F26: =SUM(F24:F25) -> -3783.4757 | G26: =SUM(G24:G25) -> -4844.9624 | H26: =SUM(H24:H25) -> -6049.4169
B28: Effect of fluctuation in foreign currency translation reserve | C28: 775.9581 | D28: 2248.1669 | E28: 9930.8997 | F28: =$C$46 -> 9930.8997 | G28: =$C$46 -> 9930.8997 | H28: =$C$46 -> 9930.8997
B29: Net Change in Cash | C29: =C14+C21+C26+C28 -> 8260.3878 | D29: =D14+D21+D26+D28 -> 31360.639 | E29: =E14+E21+E26+E28 -> 43910.265 | F29: =F14+F21+F26+F28 -> 52198.228 | G29: =G14+G21+G26+G28 -> 59681.221 | H29: =H14+H21+H26+H28 -> 67902.186
B31: Cash and cash equivalents at the beginning of the year | C31: 318311.91 | D31: ='[1]SBI BS Forecasting'!C18+'[1]SBI BS Forecasting'!C19 -> 326572.3 | E31: ='[1]SBI BS Forecasting'!D18+'[1]SBI BS Forecasting'!D19 -> 357932.94 | F31: ='SBI BS Forecasting'!E18+'SBI BS Forecasting'!E19 -> 401843.21 | G31: ='SBI BS Forecasting'!F18+'SBI BS Forecasting'!F19 -> 454041.44 | H31: ='SBI BS Forecasting'!G18+'SBI BS Forecasting'!G19 -> 513722.66
B32: Cash and cash equivalents at the end of the year | C32: =C29+C31 -> 326572.3 | D32: =D31+D29 -> 357932.94 | E32: =E31+E29 -> 401843.21 | F32: =F31+F29 -> 454041.44 | G32: =G31+G29 -> 513722.66 | H32: =H31+H29 -> 581624.84
B35: Key Forecast Assumptions (applied 2027-2029)
B36: Driver / Assumption | C36: Value | D36: Basis / Note
B37: Depreciation growth | C37: =AVERAGE(D9/C9-1,E9/D9-1) -> 0.12349547 | D37: Formula: avg YoY growth, FY2024-FY2026 (row 9)
B38: Other Operating Activities (% of Net Revenue) | C38: =AVERAGE(C10/'SBI IS Forecasting'!C11,D10/'SBI IS Forecasting'!D11,E10/'SBI IS Forecasting'!E11) -> 0.053986535 | D38: Formula: AVERAGE of ratio to 'SBI IS Forecasting' Net Revenue (row 11) each year, FY2024-FY2026
B39: Tax paid growth | C39: =AVERAGE(D11/C11-1,E11/D11-1) -> 0.077803122 | D39: Formula: avg YoY growth, FY2024-FY2026 (row 11)
B40: Change in NWC (% of Advances) | C40: =AVERAGE(C12/'SBI BS Forecasting'!C21,D12/'SBI BS Forecasting'!D21,E12/'SBI BS Forecasting'!E21) -> -0.01330717 | D40: Formula: AVERAGE of ratio to 'SBI BS Forecasting' Advances (row 21) each year, FY2024-FY2026
B41: Purchase/Sale of Investments growth | C41: ='SBI BS Forecasting'!$C$36 -> 0.057407218 | D41: Formula: linked directly to 'SBI BS Forecasting' Investments growth assumption for consistency
B42: Capex (% of prior-year Fixed Assets) | C42: =AVERAGE(-D19/'SBI BS Forecasting'!C22,-E19/'SBI BS Forecasting'!D22) -> 0.15328392 | D42: Formula: AVERAGE of (Purchase of FA / prior-year Fixed Assets) for FY2025 and FY2026
B43: Income from Investments in Associates (Rs Cr, flat p.a.) | C43: =E20 -> 0.9299 | D43: Formula: =E20, i.e. held flat at FY2026 actual (small, historically too volatile to extrapolate)
B44: Dividend payout ratio (% of Net Profit) | C44: =AVERAGE(-C24/'SBI IS Forecasting'!C22,-D24/'SBI IS Forecasting'!D22,-E24/'SBI IS Forecasting'!E22) -> 0.15944044 | D44: Formula: AVERAGE of (-Dividend paid / Net Profit) each year, referencing 'SBI IS Forecasting'
B45: Other Financing Activities growth | C45: =AVERAGE('SBI BS Forecasting'!$C$33,'SBI BS Forecasting'!$C$34) -> 0.10842974 | D45: Formula: AVERAGE of 'SBI BS Forecasting' Deposits growth and Borrowings growth assumptions (normalizes an otherwise extreme, small-base historical growth rate)
B46: FX Translation Effect (Rs Cr, flat p.a.) | C46: =E28 -> 9930.8997 | D46: Formula: =E28, i.e. held flat at FY2026 actual (inherently unpredictable currency effect)

Sheet HDFC IS
B1: HDFC Bank Limited
B3: Income Statement (2024-2026)
B4: INR ( Rupees in Crores)
B5: Line Items | C5: 2024 | D5: 2025 | E5: 2026
B7: Interest Earned | C7: 283649.02 | D7: 336367.43 | E7: 348615.15
B8: Interest Expense | C8: 154138.55 | D8: 183894.2 | E8: 185491.23
B9: Net Interest Income | C9: =C7-C8 -> 129510.47 | D9: =D7-D8 -> 152473.23 | E9: =E7-E8 -> 163123.92
B10: Other Income | C10: 124345.75 | D10: 134548.5 | E10: 146847.66
B11: Net Revenue | C11: =C9+C10 -> 253856.22 | D11: =D9+D10 -> 287021.73 | E11: =E9+E10 -> 309971.58
B13: Operating expenses | C13: 152269.34 | D13: 176605.07 | E13: 181173.91
B14: Operating Income | C14: =C11-C13 -> 101586.88 | D14: =D11-D13 -> 110416.66 | E14: =E11-E13 -> 128797.67
B16: Provisions and contingencies (ex-tax) | C16: 26057.36 | D16: 15845.79 | E16: 29080.81
B17: Net Profit Before Taxation | C17: =C14-C16 -> 75529.52 | D17: =D14-D16 -> 94570.87 | E17: =E14-E16 -> 99716.86
B18: Taxation | C18: 10083.02 | D18: 21130.7 | E18: 20497.4
B19: Net Profit After taxation | C19: =C17-C18 -> 65446.5 | D19: =D17-D18 -> 73440.17 | E19: =E17-E18 -> 79219.46
B20: Less: Minority Interest | C20: 1384.46 | D20: 2647.92 | E20: 3193.49
B21: Net Profit | C21: =C19-C20 -> 64062.04 | D21: =D19-D20 -> 70792.25 | E21: =E19-E20 -> 76025.97
B23: Basic EPS | C23: =(C21)/C24 -> 45.21 | D23: =(D21)/D24 -> 46.404149 | E23: =(E21)/E24 -> 49.504253
B24: Basic Shares | C24: 1416.9883 | D24: 1525.5586 | E24: 1535.7462
B25: Diluted EPS | C25: =(C21)/C26 -> 45.005 | D25: =(D21)/D26 -> 46.197156 | E25: =(E21)/E26 -> 49.278068
B26: Diluted Shares | C26: 1423.4427 | D26: 1532.3941 | E26: 1542.7953

Sheet HDFC BS
B1: HDFC Bank Limited
B3: Balance Sheet (2024-2026)
B4: INR ( Rupees in Crores)
B5: Line Items | C5: 2024 | D5: 2025 | E5: 2026
B7: Capital and Liabilities
B8: Capital | C8: 759.69 | D8: 765.22 | E8: 1539.34
B9: Reserves & Surplus | C9: 452982.84 | D9: 517218.98 | E9: 579975.02
B10: Minority Interest & Other Equity | C10: 16036.12 | D10: 20164.23 | E10: 26930.07
B12: Deposits | C12: 2376887.3 | D12: 2710898.2 | E12: 3099638.3
B13: Borrowings | C13: 730615.46 | D13: 634605.57 | E13: 588484.55
B14: Other Liabilities and Provisions | C14: 452912.87 | D14: 508765.19 | E14: 611473.57
B15: Total Capital and Liabilities | C15: =SUM(C8:C14) -> 4030194.3 | D15: =SUM(D8:D14) -> 4392417.4 | E15: =SUM(E8:E14) -> 4908040.8
B17: Assets
B18: Cash and Balances with Reserve Bank of India | C18: 178718.67 | D18: 144390.25 | E18: 200707.11
B19: Balances with Banks and Money at Call & Short Notice | C19: 50115.84 | D19: 105557.65 | E19: 111218.94
B20: Investments | C20: 1005681.6 | D20: 1186472.9 | E20: 1280216.3
B21: Advances | C21: 2571916.6 | D21: 2724938.2 | E21: 3050783.2
B22: Fixed Assets | C22: 12603.76 | D22: 15257.94 | E22: 16491.59
B23: Other Assets | C23: 211157.71 | D23: 215800.53 | E23: 248623.68
B24: Total Assets | C24: =SUM(C17:C23) -> 4030194.3 | D24: =SUM(D17:D23) -> 4392417.4 | E24: =SUM(E17:E23) -> 4908040.8
B26: CET 1 Capital | C26: 402231.82 | D26: 458210.41 | E26: 514070.42
B27: Tier 1 Capital | C27: 414281.32 | D27: 470466.91 | E27: 527282.92
B28: Tier 2 Capital | C28: 49721.5 | D28: 49575.61 | E28: 58933.47
B29: Total Capital (Tier1 + Tier 2) | C29: =C27+C28 -> 464002.82 | D29: =D27+D28 -> 520042.52 | E29: =E27+E28 -> 586216.39
B30: Risk-Weighted Assets | C30: 2468028.1 | D30: 2660003.9 | E30: 2974116.6
B32: Total Employees | C32: 213527 | D32: 214521 | E32: 211178

Sheet HDFC CF
B1: HDFC Bank Limited
B3: Cash Flow (2024-2026)
B4: INR ( Rupees in Crores)
B5: Line Items | C5: 2024 | D5: 2025 | E5: 2026
B7: Cash Flow From Operating Activites
B8: Net Profit/(Loss) before taxes (including share in profit from associates and net of minority interest) | C8: ='HDFC IS'!C21+'HDFC IS'!C18+'HDFC IS'!C20-345.38 -> 75184.14 | D8: ='HDFC IS'!D21+'HDFC IS'!D18+'HDFC IS'!D20-976.74 -> 93594.13 | E8: ='HDFC IS'!E21+'HDFC IS'!E18+'HDFC IS'!E20-768.9 -> 98947.96
B9: Depreciation on Fixed Assets | C9: 3092.08 | D9: 3805.23 | E9: 4194.9
B10: Other Operating Activities | C10: 13342.18 | D10: 20242.8 | E10: 30402.47
B11: Tax refund / (Taxes paid) | C11: -22842.84 | D11: 29308.36 | E11: -22656.37
B12: Change in Net Working Capital | C12: -49706.22 | D12: -19708.68 | E12: 2617.42
B14: Total Cash Flow From Operating Activites | C14: =C8+C9+C1+C10+C11+C12 -> 19069.34 | D14: =D8+D9+D1+D10+D11+D12 -> 127241.84 | E14: =E8+E9+E1+E10+E11+E12 -> 113506.38
B16: Cash Flow From Investing Activites
B17: Purchase of Investments | C17: - | D17: - | E17: -
B18: Sale Of Investments | C18: 9500.67 | D18: 192 | E18: 9806
B19: Purchase and Sale of Fixed Assets | C19: -4186.9 | D19: -3975.17 | E19: -3362.41
B20: Income from Investments in Associates | C20: - | D20: -67.47 | E20: -80.87
B21: Total Cash Flow From Investing Activites | C21: =SUM(C17:C20) -> 5313.77 | D21: =SUM(D17:D20) -> -3850.64 | E21: =SUM(E17:E20) -> 6362.72
B23: Cash Flow From Financing Activites
B24: Dividend paid | C24: -8404.42 | D24: -14826.19 | E24: -20705.98
B25: Other Financing Activities | C25: 4421.36 | D25: -87651.35 | E25: -38298.87
B26: Total Cash Flow From Financing Activites | C26: =SUM(C24:C25) -> -3983.06 | D26: =SUM(D24:D25) -> -102477.54 | E26: =SUM(E24:E25) -> -59004.85
B28: Effect of fluctuation in foreign currency translation reserve | C28: 104.94 | D28: 199.73 | E28: 1113.9
B29: Net Change in Cash | C29: =C14+C21+C26+C28 -> 20504.99 | D29: =D14+D21+D26+D28 -> 21113.39 | E29: =E14+E21+E26+E28 -> 61978.15
B31: Cash and cash equivalents at the beginning of the year | C31: 208329.52 | D31: ='HDFC BS'!C18+'HDFC BS'!C19 -> 228834.51 | E31: ='HDFC BS'!D18+'HDFC BS'!D19 -> 249947.9
B32: Cash and cash equivalents at the end of the year | C32: =C29+C31 -> 228834.51 | D32: =D31+D29 -> 249947.9 | E32: =E31+E29 -> 311926.05

Sheet Ratio Analysis
B1: State Bank Of India | G1: VS | I1: HDFC Bank Limited
B3: Income Statement Growth Horizontal | I3: Income Statement Growth Horizontal
B4: INR ( Rupees in Crores) | I4: INR ( Rupees in Crores)
B5: Category | C5: Ratios | D5: 2024 | E5: 2025 | F5: 2026 | I5: Category | J5: Ratios | K5: 2024 | L5: 2025 | M5: 2026 | N5: Comments
B6: Profitability | C6: ROA | D6: ='SBI IS'!C22/'SBI BS'!C24 -> 0.0099624096 | E6: ='SBI IS'!D22/'SBI BS'!D24 -> 0.010604234 | F6: ='SBI IS'!E22/'SBI BS'!E24 -> 0.010009986 | I6: Profitability | J6: ROA | K6: ='HDFC IS'!C21/'HDFC BS'!C24 -> 0.015895522 | L6: ='HDFC IS'!D21/'HDFC BS'!D24 -> 0.016116922 | M6: ='HDFC IS'!E21/'HDFC BS'!E24 -> 0.015490085 | N6: HDFC generates a meaningfully higher Return on Assets than SBI across all three years, reflecting a more profitable, fee/retail-heavy asset base versus SBI's larger, lower-yielding balance sheet.
B7: Profitability | C7: ROE | D7: ='SBI IS'!C22/('SBI BS'!C8+'SBI BS'!C9+'SBI BS'!C10) -> 0.15580897 | E7: ='SBI IS'!D22/('SBI BS'!D8+'SBI BS'!D9+'SBI BS'!D10) -> 0.15356777 | F7: ='SBI IS'!E22/('SBI BS'!E8+'SBI BS'!E9+'SBI BS'!E10) -> 0.13546739 | I7: Profitability | J7: ROE | K7: ='HDFC IS'!C21/('HDFC BS'!C8+'HDFC BS'!C9+'HDFC BS'!C10) -> 0.13636644 | L7: ='HDFC IS'!D21/('HDFC BS'!D8+'HDFC BS'!D9+'HDFC BS'!D10) -> 0.13154781 | M7: ='HDFC IS'!E21/('HDFC BS'!E8+'HDFC BS'!E9+'HDFC BS'!E10) -> 0.12495138 | N7: SBI's Return on Equity is higher than HDFC's, mainly because SBI runs on a much thinner equity base relative to assets (higher leverage), which lifts ROE even though its ROA is lower.
B8: Profitability | C8: NIM | D8: ='SBI IS'!C9/('SBI BS'!C21+'SBI BS'!C20) -> 0.030442395 | E8: ='SBI IS'!D9/('SBI BS'!D21+'SBI BS'!D20) -> 0.029330343 | F8: ='SBI IS'!E9/('SBI BS'!E21+'SBI BS'!E20) -> 0.027247341 | I8: Profitability | J8: NIM | K8: ='HDFC IS'!C9/('HDFC BS'!C21+'HDFC BS'!C20) -> 0.036200395 | L8: ='HDFC IS'!D9/('HDFC BS'!D21+'HDFC BS'!D20) -> 0.038981643 | M8: ='HDFC IS'!E9/('HDFC BS'!E21+'HDFC BS'!E20) -> 0.037664266 | N8: HDFC's Net Interest Margin is consistently wider than SBI's, indicating HDFC earns more spread on its advances and investments; SBI's NIM has also been gradually compressing over the period.
B9: Profitability | C9: Net Profit Margin | D9: ='SBI IS'!C22/'SBI IS'!C11 -> 0.2003491 | E9: ='SBI IS'!D22/'SBI IS'!D11 -> 0.21402136 | F9: ='SBI IS'!E22/'SBI IS'!E11 -> 0.20948359 | I9: Profitability | J9: Net Profit Margin | K9: ='HDFC IS'!C21/'HDFC IS'!C11 -> 0.25235561 | L9: ='HDFC IS'!D21/'HDFC IS'!D11 -> 0.24664422 | M9: ='HDFC IS'!E21/'HDFC IS'!E11 -> 0.24526755 | N9: HDFC converts a larger share of Net Revenue into Net Profit than SBI in every year, consistent with HDFC's better cost efficiency and asset quality.
B10: Profitability | C10: Cost-to-Income Ratio | D10: ='SBI IS'!C13/'SBI IS'!C11 -> 0.7044996 | E10: ='SBI IS'!D13/'SBI IS'!D11 -> 0.65279672 | F10: ='SBI IS'!E13/'SBI IS'!E11 -> 0.66052533 | I10: Profitability | J10: Cost-to-Income Ratio | K10: ='HDFC IS'!C13/'HDFC IS'!C11 -> 0.59982513 | L10: ='HDFC IS'!D13/'HDFC IS'!D11 -> 0.61530209 | M10: ='HDFC IS'!E13/'HDFC IS'!E11 -> 0.58448555 | N10: HDFC's Cost-to-Income Ratio is lower than SBI's, showing HDFC keeps a smaller share of revenue tied up in operating expenses; SBI has improved this ratio since FY2024 but still lags HDFC.
B11: Profitability | C11: PPOP Margin | D11: ='SBI IS'!C14/'SBI IS'!C11 -> 0.2955004 | E11: ='SBI IS'!D14/'SBI IS'!D11 -> 0.34720328 | F11: ='SBI IS'!E14/'SBI IS'!E11 -> 0.33947467 | I11: Profitability | J11: PPOP Margin | K11: ='HDFC IS'!C14/'HDFC IS'!C11 -> 0.40017487 | L11: ='HDFC IS'!D14/'HDFC IS'!D11 -> 0.38469791 | M11: ='HDFC IS'!E14/'HDFC IS'!E11 -> 0.41551445 | N11: HDFC's Pre-Provision Operating Profit Margin is higher than SBI's in most years, mirroring its lower cost-to-income ratio and stronger core operating profitability.
B12: Profitability | C12: Operating Expense Ratio | D12: ='SBI IS'!C13/'SBI BS'!C24 -> 0.035031421 | E12: ='SBI IS'!D13/'SBI BS'!D24 -> 0.03234448 | F12: ='SBI IS'!E13/'SBI BS'!E24 -> 0.031562613 | I12: Profitability | J12: Operating Expense Ratio | K12: ='HDFC IS'!C13/'HDFC BS'!C24 -> 0.037782134 | L12: ='HDFC IS'!D13/'HDFC BS'!D24 -> 0.040206805 | M12: ='HDFC IS'!E13/'HDFC BS'!E24 -> 0.036913692 | N12: Both banks keep Operating Expenses at a similar, low percentage of Total Assets, with SBI slightly more efficient on this basis in FY2026 despite its larger, lower-margin balance sheet.
B13: Liquidity | C13: Loan-to-Deposit Ratio | D13: ='SBI BS'!C21/'SBI BS'!C12 -> 0.76195391 | E13: ='SBI BS'!D21/'SBI BS'!D12 -> 0.78141736 | F13: ='SBI BS'!E21/'SBI BS'!E12 -> 0.82375198 | I13: Liquidity | J13: Loan-to-Deposit Ratio | K13: ='HDFC BS'!C21/'HDFC BS'!C12 -> 1.0820524 | L13: ='HDFC BS'!D21/'HDFC BS'!D12 -> 1.0051791 | M13: ='HDFC BS'!E21/'HDFC BS'!E12 -> 0.98423846 | N13: HDFC's Loan-to-Deposit Ratio is well above 100% in FY2024 and stays near parity thereafter, showing it lends out close to (or more than) its deposit base; SBI runs a more conservative, sub-85% ratio with room to grow advances.
B14: Liquidity | C14: Liquid Assets / Total Assets | D14: =('SBI BS'!C18+'SBI BS'!C19+'SBI BS'!C20)/'SBI BS'!C24 -> 0.36192465 | E14: =('SBI BS'!D18+'SBI BS'!D19+'SBI BS'!D20)/'SBI BS'!D24 -> 0.35048798 | F14: =('SBI BS'!E18+'SBI BS'!E19+'SBI BS'!E20)/'SBI BS'!E24 -> 0.33182991 | I14: Liquidity | J14: Liquid Assets / Total Assets | K14: =('HDFC BS'!C18+'HDFC BS'!C19+'HDFC BS'!C20)/'HDFC BS'!C24 -> 0.30631678 | L14: =('HDFC BS'!D18+'HDFC BS'!D19+'HDFC BS'!D20)/'HDFC BS'!D24 -> 0.32702283 | M14: =('HDFC BS'!E18+'HDFC BS'!E19+'HDFC BS'!E20)/'HDFC BS'!E24 -> 0.32439468 | N14: SBI holds a larger share of Total Assets in liquid form (cash, interbank balances and investments) than HDFC, consistent with its more conservative balance sheet mix.
B15: Liquidity | C15: Liquid Assets / Deposits | D15: =('SBI BS'!C18+'SBI BS'!C19+'SBI BS'!C20)/'SBI BS'!C12 -> 0.49070817 | E15: =('SBI BS'!D18+'SBI BS'!D19+'SBI BS'!D20)/'SBI BS'!D12 -> 0.47124671 | F15: =('SBI BS'!E18+'SBI BS'!E19+'SBI BS'!E20)/'SBI BS'!E12 -> 0.45694208 | I15: Liquidity | J15: Liquid Assets / Deposits | K15: =('HDFC BS'!C18+'HDFC BS'!C19+'HDFC BS'!C20)/'HDFC BS'!C12 -> 0.51938354 | L15: =('HDFC BS'!D18+'HDFC BS'!D19+'HDFC BS'!D20)/'HDFC BS'!D12 -> 0.52986895 | M15: =('HDFC BS'!E18+'HDFC BS'!E19+'HDFC BS'!E20)/'HDFC BS'!E12 -> 0.51365424 | N15: HDFC holds slightly more liquid assets relative to its deposit base than SBI, even though HDFC's loan book is proportionally larger, pointing to a well-buffered liquidity position.
B16: Liquidity | C16: Cash & RBI / Deposits | D16: ='SBI BS'!C18/'SBI BS'!C12 -> 0.045374939 | E16: ='SBI BS'!D18/'SBI BS'!D12 -> 0.041817908 | F16: ='SBI BS'!E18/'SBI BS'!E12 -> 0.044460933 | I16: Liquidity | J16: Cash & RBI / Deposits | K16: ='HDFC BS'!C18/'HDFC BS'!C12 -> 0.075190217 | L16: ='HDFC BS'!D18/'HDFC BS'!D12 -> 0.053262881 | M16: ='HDFC BS'!E18/'HDFC BS'!E12 -> 0.064751784 | N16: HDFC keeps a higher proportion of Cash & RBI balances against deposits than SBI in every year, though both banks show some year-to-year fluctuation in this cushion.
B17: Liquidity | C17: Cash & RBI / Total Assets | D17: ='SBI BS'!C18/'SBI BS'!C24 -> 0.033466549 | E17: ='SBI BS'!D18/'SBI BS'!D24 -> 0.031101913 | F17: ='SBI BS'!E18/'SBI BS'!E24 -> 0.032287391 | I17: Liquidity | J17: Cash & RBI / Total Assets | K17: ='HDFC BS'!C18/'HDFC BS'!C24 -> 0.044344927 | L17: ='HDFC BS'!D18/'HDFC BS'!D24 -> 0.032872616 | M17: ='HDFC BS'!E18/'HDFC BS'!E24 -> 0.040893529 | N17: Cash & RBI balances make up a slightly larger share of Total Assets for HDFC than for SBI, though both ratios are relatively stable and modest in size.
B18: Growth Ratios | C18: Loan Growth | D18: - | E18: =('SBI BS'!D21-'SBI BS'!C21)/'SBI BS'!C21 -> 0.1232887 | F18: =('SBI BS'!E21-'SBI BS'!D21)/'SBI BS'!D21 -> 0.17106832 | I18: Growth Ratios | J18: Loan Growth | K18: - | L18: =('HDFC BS'!D21-'HDFC BS'!C21)/'HDFC BS'!C21 -> 0.059497072 | M18: =('HDFC BS'!E21-'HDFC BS'!D21)/'HDFC BS'!D21 -> 0.11957889 | N18: HDFC's loan book grew more slowly than SBI's in FY2025 but closed the gap in FY2026; SBI has shown consistently strong double-digit advances growth across both years.
B19: Growth Ratios | C19: Deposit Growth | D19: - | E19: =('SBI BS'!D12-'SBI BS'!C12)/'SBI BS'!C12 -> 0.095309969 | F19: =('SBI BS'!E12-'SBI BS'!D12)/'SBI BS'!D12 -> 0.11088427 | I19: Growth Ratios | J19: Deposit Growth | K19: - | L19: =('HDFC BS'!D12-'HDFC BS'!C12)/'HDFC BS'!C12 -> 0.14052452 | M19: =('HDFC BS'!E12-'HDFC BS'!D12)/'HDFC BS'!D12 -> 0.14339899 | N19: HDFC has grown deposits faster than SBI in both years, which helps explain why HDFC's Loan-to-Deposit ratio has been able to ease down from FY2024 while still funding strong loan growth.
B20: Growth Ratios | C20: NII Growth | D20: - | E20: =('SBI IS'!D9-'SBI IS'!C9)/'SBI IS'!C9 -> 0.055261985 | F20: =('SBI IS'!E9-'SBI IS'!D9)/'SBI IS'!D9 -> 0.055755684 | I20: Growth Ratios | J20: NII Growth | K20: - | L20: =('HDFC IS'!D9-'HDFC IS'!C9)/'HDFC IS'!C9 -> 0.17730428 | M20: =('HDFC IS'!E9-'HDFC IS'!D9)/'HDFC IS'!D9 -> 0.069852852 | N20: HDFC's Net Interest Income grew sharply in FY2025 before slowing in FY2026, while SBI's NII growth has been steadier but more modest across both years.
B21: Growth Ratios | C21: Net Profit Growth | D21: - | E21: =('SBI IS'!D22-'SBI IS'!C22)/'SBI IS'!C22 -> 0.15617092 | F21: =('SBI IS'!E22-'SBI IS'!D22)/'SBI IS'!D22 -> 0.073973059 | I21: Growth Ratios | J21: Net Profit Growth | K21: - | L21: =('HDFC IS'!D21-'HDFC IS'!C21)/'HDFC IS'!C21 -> 0.10505769 | M21: =('HDFC IS'!E21-'HDFC IS'!D21)/'HDFC IS'!D21 -> 0.073930692 | N21: SBI posted stronger Net Profit growth than HDFC in FY2025, though growth decelerated for both banks by FY2026, converging to a similar mid-single-digit pace.
B22: Growth Ratios | C22: Total Asset Growth | D22: - | E22: =('SBI BS'!D24-'SBI BS'!C24)/'SBI BS'!C24 -> 0.086193289 | F22: =('SBI BS'!E24-'SBI BS'!D24)/'SBI BS'!D24 -> 0.13773007 | I22: Growth Ratios | J22: Total Asset Growth | K22: - | L22: =('HDFC BS'!D24-'HDFC BS'!C24)/'HDFC BS'!C24 -> 0.089877345 | M22: =('HDFC BS'!E24-'HDFC BS'!D24)/'HDFC BS'!D24 -> 0.11738944 | N22: SBI's Total Assets grew faster than HDFC's in FY2026, though HDFC posted the faster growth in FY2025; overall balance-sheet expansion has been broadly comparable between the two banks.
B23: Growth Ratios | C23: Net Revenue Growth | D23: - | E23: =('SBI IS'!D11-'SBI IS'!C11)/'SBI IS'!C11 -> 0.082311611 | F23: =('SBI IS'!E11-'SBI IS'!D11)/'SBI IS'!D11 -> 0.097237141 | I23: Growth Ratios | J23: Net Revenue Growth | K23: - | L23: =('HDFC IS'!D11-'HDFC IS'!C11)/'HDFC IS'!C11 -> 0.13064683 | M23: =('HDFC IS'!E11-'HDFC IS'!D11)/'HDFC IS'!D11 -> 0.07995858 | N23: HDFC's Net Revenue growth outpaced SBI's in FY2025, but SBI grew revenue faster in FY2026, again showing the two banks trading places year to year.
B24: Growth Ratios | C24: Operating Income Growth | D24: - | E24: =('SBI IS'!D14-'SBI IS'!C14)/'SBI IS'!C14 -> 0.27168064 | F24: =('SBI IS'!E14-'SBI IS'!D14)/'SBI IS'!D14 -> 0.072813047 | I24: Growth Ratios | J24: Operating Income Growth | K24: - | L24: =('HDFC IS'!D14-'HDFC IS'!C14)/'HDFC IS'!C14 -> 0.086918508 | M24: =('HDFC IS'!E14-'HDFC IS'!D14)/'HDFC IS'!D14 -> 0.16646953 | N24: SBI's Operating Income growth was exceptionally strong in FY2025 before slowing sharply in FY2026, while HDFC shows the opposite pattern — accelerating operating income growth into FY2026.
B25: Growth Ratios | C25: Investment Growth | D25: - | E25: =('SBI BS'!D20-'SBI BS'!C20)/'SBI BS'!C20 -> 0.045037058 | F25: =('SBI BS'!E20-'SBI BS'!D20)/'SBI BS'!D20 -> 0.069777378 | I25: Growth Ratios | J25: Investment Growth | K25: - | L25: =('HDFC BS'!D20-'HDFC BS'!C20)/'HDFC BS'!C20 -> 0.17976987 | M25: =('HDFC BS'!E20-'HDFC BS'!D20)/'HDFC BS'!D20 -> 0.079010149 | N25: HDFC grew its investment book considerably faster than SBI in FY2025, though both banks posted more modest, closer investment growth in FY2026.
B26: Asset Quality | C26: Gross NPA Ratio | D26: 2.24 | E26: 1.82 | F26: 1.49 | I26: Asset Quality | J26: Gross NPA Ratio | K26: 1.24 | L26: 1.33 | M26: 1.15 | N26: HDFC Bank has fewer bad loans compared with SBI, meaning HDFC's loan quality is better.
B27: Asset Quality | C27: Net NPA Ratio | D27: 0.57 | E27: 0.47 | F27: 0.39 | I27: Asset Quality | J27: Net NPA Ratio | K27: 0.33 | L27: 0.43 | M27: 0.38 | N27: HDFC also has fewer bad loans after adjusting for provisions, while SBI has improved significantly over the three years.
B28: Asset Quality | C28: Provision Coverage Ratio | D28: 91.89 | E28: 92.08 | F28: 91.97 | I28: Asset Quality | J28: Provision Coverage Ratio | K28: 74.04 | L28: 67.86 | M28: 67.21 | N28: SBI's Provision Coverage Ratio is significantly higher than HDFC's throughout, meaning SBI has provided for a larger share of its bad loans, which is a more conservative buffer against credit losses.
B29: Capital Adequacy | C29: CET1 Ratio | D29: 10.36 | E29: 10.81 | F29: 12.29 | I29: Capital Adequacy | J29: CET1 Ratio | K29: 16.3 | L29: 17.23 | M29: 17.28 | N29: HDFC's CET1 Ratio is well above SBI's in every year, giving HDFC a thicker core-equity capital cushion, even as SBI's CET1 has been improving steadily.
B30: Capital Adequacy | C30: Tier 1 Ratio | D30: 11.93 | E30: 12.11 | F30: 13.33 | I30: Capital Adequacy | J30: Tier 1 Ratio | K30: 16.79 | L30: 17.69 | M30: 17.73 | N30: HDFC maintains a higher Tier 1 Ratio than SBI across all three years, though SBI's Tier 1 capital position has strengthened noticeably by FY2026.
B31: Capital Adequacy | C31: Tier 2 Ratio | D31: 2.35 | E31: 2.14 | F31: 2.07 | I31: Capital Adequacy | J31: Tier 2 Ratio | K31: 2.01 | L31: 1.86 | M31: 1.98 | N31: Tier 2 Ratios are broadly similar and modest for both banks, with SBI holding a marginally larger Tier 2 cushion than HDFC in most years.
B32: Capital Adequacy | C32: CRAR | D32: 14.28 | E32: 14.25 | F32: 15.4 | I32: Capital Adequacy | J32: CRAR | K32: ='HDFC BS'!C29/'HDFC BS'!C30*100 -> 18.800549 | L32: ='HDFC BS'!D29/'HDFC BS'!D30*100 -> 19.550442 | M32: ='HDFC BS'!E29/'HDFC BS'!E30*100 -> 19.710606 | N32: HDFC's overall Capital to Risk-weighted Assets Ratio (CRAR) is markedly higher than SBI's, underscoring HDFC's stronger overall capital adequacy position.
B33: Capital Adequacy | C33: Leverage Ratio | D33: 5.67 | E33: 6.01 | F33: 6.25 | I33: Capital Adequacy | J33: Leverage Ratio | K33: 10.4 | L33: 10.91 | M33: 10.99 | N33: HDFC's Leverage Ratio is nearly double SBI's, indicating HDFC holds proportionally more Tier 1 capital against its balance sheet size than SBI does.
B34: Efficiency | C34: Cost-to-Income | D34: ='SBI IS'!C13/'SBI IS'!C11 -> 0.7044996 | E34: ='SBI IS'!D13/'SBI IS'!D11 -> 0.65279672 | F34: ='SBI IS'!E13/'SBI IS'!E11 -> 0.66052533 | I34: Efficiency | J34: Cost-to-Income | K34: ='HDFC IS'!C13/'HDFC IS'!C11 -> 0.59982513 | L34: ='HDFC IS'!D13/'HDFC IS'!D11 -> 0.61530209 | M34: ='HDFC IS'!E13/'HDFC IS'!E11 -> 0.58448555 | N34: (Same as Cost-to-Income Ratio above) HDFC continues to operate more efficiently than SBI on a cost-to-revenue basis across all three years.
B35: Efficiency | C35: Asset Utilization | D35: ='SBI IS'!C11/'SBI BS'!C24 -> 0.049725253 | E35: ='SBI IS'!D11/'SBI BS'!D24 -> 0.049547552 | F35: ='SBI IS'!E11/'SBI BS'!E24 -> 0.047784107 | I35: Efficiency | J35: Asset Utilization | K35: ='HDFC IS'!C11/'HDFC BS'!C24 -> 0.062988582 | L35: ='HDFC IS'!D11/'HDFC BS'!D24 -> 0.065344821 | M35: ='HDFC IS'!E11/'HDFC BS'!E24 -> 0.063155868 | N35: HDFC generates more Net Revenue per unit of Total Assets than SBI, consistent with HDFC's higher-yielding, more fee-oriented business mix.
B36: Efficiency | C36: Profit per Employee | D36: =('SBI IS'!C22/'SBI BS'!C32)*100 -> 28.878957 | E36: =('SBI IS'!D22/'SBI BS'!D32)*100 -> 32.833531 | F36: =('SBI IS'!E22/'SBI BS'!E32)*100 -> 33.981335 | I36: Efficiency | J36: Profit per Employee | K36: =('HDFC IS'!C21/'HDFC BS'!C32)*100 -> 30.001845 | L36: =('HDFC IS'!D21/'HDFC BS'!D32)*100 -> 33.000149 | M36: =('HDFC IS'!E21/'HDFC BS'!E32)*100 -> 36.000895 | N36: HDFC generates modestly higher Net Profit per Employee than SBI in every year, though SBI's per-employee profitability has been rising at a faster pace, partly closing the gap by FY2026.

Sheet HDFC IS Forecasting
B1: HDFC Bank Limited
B3: Income Statement Forecast (2024-2029)
B4: INR ( Rupees in Crores)
B5: Line Items | C5: 2024 | D5: 2025 | E5: 2026 | F5: 2027 | G5: 2028 | H5: 2029
B7: Interest Earned | C7: 283649.02 | D7: 336367.43 | E7: 348615.15 | F7: =E7*(1+$C$31) -> 387358.43 | G7: =F7*(1+$C$31) -> 430407.44 | H7: =G7*(1+$C$31) -> 478240.69
B8: Interest Expense | C8: 154138.55 | D8: 183894.2 | E8: 185491.23 | F8: =E8*(1+$C$32) -> 204200.74 | G8: =F8*(1+$C$32) -> 224797.38 | H8: =G8*(1+$C$32) -> 247471.49
B9: Net Interest Income | C9: =C7-C8 -> 129510.47 | D9: =D7-D8 -> 152473.23 | E9: =E7-E8 -> 163123.92 | F9: =F7-F8 -> 183157.69 | G9: =G7-G8 -> 205610.06 | H9: =H7-H8 -> 230769.19
B10: Other Income | C10: 124345.75 | D10: 134548.5 | E10: 146847.66 | F10: =E10*(1+$C$33) -> 159583.91 | G10: =F10*(1+$C$33) -> 173424.79 | H10: =G10*(1+$C$33) -> 188466.1
B11: Net Revenue | C11: =C9+C10 -> 253856.22 | D11: =D9+D10 -> 287021.73 | E11: =E9+E10 -> 309971.58 | F11: =F9+F10 -> 342741.6 | G11: =G9+G10 -> 379034.84 | H11: =H9+H10 -> 419235.29
B13: Operating expenses | C13: 152269.34 | D13: 176605.07 | E13: 181173.91 | F13: =E13*(1+$C$34) -> 197995.06 | G13: =F13*(1+$C$34) -> 216377.98 | H13: =G13*(1+$C$34) -> 236467.67
B14: Operating Income | C14: =C11-C13 -> 101586.88 | D14: =D11-D13 -> 110416.66 | E14: =E11-E13 -> 128797.67 | F14: =F11-F13 -> 144746.54 | G14: =G11-G13 -> 162656.86 | H14: =H11-H13 -> 182767.62
B16: Provisions and contingencies (ex-tax) | C16: 26057.36 | D16: 15845.79 | E16: 29080.81 | F16: =$C$35*'HDFC BS Forecasting'!F21 -> 28230.08 | G16: =$C$35*'HDFC BS Forecasting'!G21 -> 30757.745 | H16: =$C$35*'HDFC BS Forecasting'!H21 -> 33511.731
B17: Net Profit Before Taxation | C17: =C14-C16 -> 75529.52 | D17: =D14-D16 -> 94570.87 | E17: =E14-E16 -> 99716.86 | F17: =F14-F16 -> 116516.46 | G17: =G14-G16 -> 131899.12 | H17: =H14-H16 -> 149255.89
B18: Taxation | C18: 10083.02 | D18: 21130.7 | E18: 20497.4 | F18: =F17*$C$36 -> 21846.504 | G18: =G17*$C$36 -> 24730.71 | H18: =H17*$C$36 -> 27985.056
B19: Net Profit After taxation | C19: =C17-C18 -> 65446.5 | D19: =D17-D18 -> 73440.17 | E19: =E17-E18 -> 79219.46 | F19: =F17-F18 -> 94669.951 | G19: =G17-G18 -> 107168.41 | H19: =H17-H18 -> 121270.84
B20: Less: Minority Interest | C20: 1384.46 | D20: 2647.92 | E20: 3193.49 | F20: =E20*(1+$C$38) -> 3479.2888 | G20: =F20*(1+$C$38) -> 3790.6649 | H20: =G20*(1+$C$38) -> 4129.9074
B21: Net Profit | C21: =C19-C20 -> 64062.04 | D21: =D19-D20 -> 70792.25 | E21: =E19-E20 -> 76025.97 | F21: =F19-F20 -> 91190.662 | G21: =G19-G20 -> 103377.74 | H21: =H19-H20 -> 117140.93
B23: Basic EPS | C23: =(C21)/C24 -> 45.21 | D23: =(D21)/D24 -> 46.404149 | E23: =(E21)/E24 -> 49.504253 | F23: =(F21)/F24 -> 56.73543 | G23: =(G21)/G24 -> 61.454609 | H23: =(H21)/H24 -> 66.536434
B24: Basic Shares | C24: 1416.9883 | D24: 1525.5586 | E24: 1535.7462 | F24: =E24*(1+$C$39) -> 1607.2966 | G24: =F24*(1+$C$39) -> 1682.1805 | H24: =G24*(1+$C$39) -> 1760.5532
B25: Diluted EPS | C25: =(C21)/C26 -> 45.005 | D25: =(D21)/D26 -> 46.197156 | E25: =(E21)/E26 -> 49.278068 | F25: =(F21)/F26 -> 56.73543 | G25: =(G21)/G26 -> 61.454609 | H25: =(H21)/H26 -> 66.536434
B26: Diluted Shares | C26: 1423.4427 | D26: 1532.3941 | E26: 1542.7953 | F26: =F24 -> 1607.2966 | G26: =G24 -> 1682.1805 | H26: =H24 -> 1760.5532
B29: Key Forecast Assumptions (applied 2027-2029)
B30: Driver / Assumption | C30: Value | D30: Basis / Note
B31: Interest Earned growth | C31: =AVERAGE(D7/C7-1,E7/D7-1) -> 0.11113481 | D31: Average YoY growth, FY2024-FY2026
B32: Interest Expense growth | C32: =AVERAGE(D8/C8-1,E8/D8-1) -> 0.10086467 | D32: Average YoY growth, FY2024-FY2026
B33: Other Income growth | C33: =AVERAGE(D10/C10-1,E10/D10-1) -> 0.086731032 | D33: Average YoY growth, FY2024-FY2026
B34: Operating Expenses growth | C34: =AVERAGE(D13/C13-1,E13/D13-1) -> 0.092845334 | D34: Average YoY growth, FY2024-FY2026
B35: Provisions (% of Advances) | C35: =AVERAGE(C16/'HDFC BS Forecasting'!C21,D16/'HDFC BS Forecasting'!D21,E16/'HDFC BS Forecasting'!E21) -> 0.0084929465 | D35: Avg Provisions/Advances FY2024-26; applied to 'SBI BS Forecasting' Advances
B36: Effective Tax Rate | C36: =AVERAGE(C18/C17,D18/D17,E18/E17) -> 0.18749716 | D36: Average effective tax rate (Tax/PBT), FY2024-FY2026
B37: Share in Profit of Associates growth | C37: =AVERAGE(D20/C20-1,E20/D20-1) -> 0.55931925 | D37: Average YoY growth, FY2024-FY2026
B38: Minority Interest growth | C38: =AVERAGE(D21/C21-1,E21/D21-1) -> 0.089494191 | D38: Average YoY growth, FY2024-FY2026
B39: Basic/Diluted Shares growth | C39: =AVERAGE(D25/C25-1,E25/D25-1) -> 0.046589958 | D39: Average YoY growth, FY2024-FY2026

Sheet HDFC BS Forecasting
B1: HDFC Bank Limited
B3: Balance Sheet Forecast (2024-2029)
B4: INR ( Rupees in Crores)
B5: Line Items | C5: 2024 | D5: 2025 | E5: 2026 | F5: 2027 | G5: 2028 | H5: 2029
B7: Capital and Liabilities
B8: Capital | C8: 759.69 | D8: 765.22 | E8: 1539.34 | F8: =E8*(1+$C$31) -> 2323.5644 | G8: =F8*(1+$C$31) -> 3507.3158 | H8: =G8*(1+$C$31) -> 5294.1353
B9: Reserves & Surplus | C9: 452982.84 | D9: 517218.98 | E9: 579975.02 | F9: =E9+'HDFC IS Forecasting'!F22+'HDFC CF Forecasting'!F24+$C$39 -> 642604.56 | G9: =F9+'HDFC IS Forecasting'!G22+'HDFC CF Forecasting'!G24+$C$39 -> 702743.97 | H9: =G9+'HDFC IS Forecasting'!H22+'HDFC CF Forecasting'!H24+$C$39 -> 760071.19
B10: Minority Interest & Other Equity | C10: 16036.12 | D10: 20164.23 | E10: 26930.07 | F10: =E10*(1+$C$32) -> 34914.33 | G10: =F10*(1+$C$32) -> 45265.774 | H10: =G10*(1+$C$32) -> 58686.227
B12: Deposits | C12: 2376887.3 | D12: 2710898.2 | E12: 3099638.3 | F12: =E12*(1+$C$33) -> 3539668.4 | G12: =F12*(1+$C$33) -> 4042165.9 | H12: =G12*(1+$C$33) -> 4615998.9
B13: Borrowings | C13: 730615.46 | D13: 634605.57 | E13: 588484.55 | F13: =E13*(1+$C$34) -> 528433.74 | G13: =F13*(1+$C$34) -> 474510.7 | H13: =G13*(1+$C$34) -> 426090.14
B14: Other Liabilities and Provisions | C14: 452912.87 | D14: 508765.19 | E14: 611473.57 | F14: =F24-(F8+F9+F10+F12+F13) -> 711647.57 | G14: =G24-(G8+G9+G10+G12+G13) -> 753648.28 | H14: =H24-(H8+H9+H10+H12+H13) -> 830999.93
B15: Total Capital and Liabilities | C15: =SUM(C8:C14) -> 4030194.3 | D15: =SUM(D8:D14) -> 4392417.4 | E15: =SUM(E8:E14) -> 4908040.8 | F15: =SUM(F8:F14) -> 5459592.2 | G15: =SUM(G8:G14) -> 6021841.9 | H15: =SUM(H8:H14) -> 6697140.5
B17: Assets
B18: Cash and Balances with Reserve Bank of India | C18: 178718.67 | D18: 144390.25 | E18: 200707.11 | F18: ='HDFC CF Forecasting'!F32-F19 -> 227783.08 | G18: ='HDFC CF Forecasting'!G32-G19 -> 169403.87 | H18: ='HDFC CF Forecasting'!H32-H19 -> 112168.33
B19: Balances with Banks and Money at Call & Short Notice | C19: 50115.84 | D19: 105557.65 | E19: 111218.94 | F19: =E19*(1+$C$35) -> 175720.66 | G19: =F19*(1+$C$35) -> 277630.34 | H19: =G19*(1+$C$35) -> 438642.8
B20: Investments | C20: 1005681.6 | D20: 1186472.9 | E20: 1280216.3 | F20: =E20*(1+$C$36) -> 1445863.5 | G20: =F20*(1+$C$36) -> 1632943.8 | H20: =G20*(1+$C$36) -> 1844230.4
B21: Advances | C21: 2571916.6 | D21: 2724938.2 | E21: 3050783.2 | F21: =E21*(1+$C$37) -> 3323944.2 | G21: =F21*(1+$C$37) -> 3621563.4 | H21: =G21*(1+$C$37) -> 3945830.9
B22: Fixed Assets | C22: 12603.76 | D22: 15257.94 | E22: 16491.59 | F22: =E22-'HDFC CF Forecasting'!F19-'HDFC CF Forecasting'!F9 -> 16015.975 | G22: =F22-'HDFC CF Forecasting'!G19-'HDFC CF Forecasting'!G9 -> 26510.987 | H22: =G22-'HDFC CF Forecasting'!H19-'HDFC CF Forecasting'!H9 -> 36906.067
B23: Other Assets | C23: 211157.71 | D23: 215800.53 | E23: 248623.68 | F23: =E23*(1+$C$38) -> 270264.75 | G23: =F23*(1+$C$38) -> 293789.53 | H23: =G23*(1+$C$38) -> 319361.99
B24: Total Assets | C24: =SUM(C17:C23) -> 4030194.3 | D24: =SUM(D17:D23) -> 4392417.4 | E24: =SUM(E17:E23) -> 4908040.8 | F24: =SUM(F17:F23) -> 5459592.2 | G24: =SUM(G17:G23) -> 6021841.9 | H24: =SUM(H17:H23) -> 6697140.5
B26: Balance Check (Total Assets − Total Capital & Liabilities) | C26: =C24-C15 -> 0 | D26: =D24-D15 -> 0 | E26: =E24-E15 -> 0 | F26: =F24-F15 -> 0 | G26: =G24-G15 -> 0 | H26: =H24-H15 -> 0
B29: Key Forecast Assumptions (applied 2027-2029)
B30: Driver / Assumption | C30: Value | D30: Basis / Note
B31: Capital growth | C31: =AVERAGE(D8/C8-1,E8/D8-1) -> 0.50945496 | D31: Formula: avg YoY growth, FY2024-FY2026 (row 8)
B32: Minority Interest & Other Equity growth | C32: =AVERAGE(D10/C10-1,E10/D10-1) -> 0.29648124 | D32: Formula: avg YoY growth, FY2024-FY2026 (row 10)
B33: Deposits growth | C33: =AVERAGE(D12/C12-1,E12/D12-1) -> 0.14196175 | D33: Formula: avg YoY growth, FY2024-FY2026 (row 12)
B34: Borrowings growth | C34: =AVERAGE(D13/C13-1,E13/D13-1) -> -0.10204314 | D34: Formula: avg YoY growth, FY2024-FY2026 (row 13)
B35: Balances with Banks & Money at Call growth | C35: =AVERAGE(D19/C19-1,E19/D19-1) -> 0.5799527 | D35: Formula: avg YoY growth, FY2024-FY2026 (row 19)
B36: Investments growth | C36: =AVERAGE(D20/C20-1,E20/D20-1) -> 0.12939001 | D36: Formula: avg YoY growth, FY2024-FY2026 (row 20)
B37: Advances growth | C37: =AVERAGE(D21/C21-1,E21/D21-1) -> 0.089537979 | D37: Formula: avg YoY growth, FY2024-FY2026 (row 21)
B38: Other Assets growth | C38: =AVERAGE(D23/C23-1,E23/D23-1) -> 0.08704347 | D38: Formula: avg YoY growth, FY2024-FY2026 (row 23)
B39: Other Reserve Movements (Rs Cr, flat p.a.) | C39: =AVERAGE((D9-C9)-('HDFC IS Forecasting'!D22+'HDFC CF Forecasting'!D24),(E9-D9)-('HDFC IS Forecasting'!E22+'HDFC CF Forecasting'!E24)) -> 81262.175 | D39: Formula: AVERAGE of (actual reserve change less Net Profit less Dividends) for FY2025 and FY2026 - captures OCI/associate equity pickup etc. not modeled elsewhere
B40: Other Liabilities and Provisions | C40: Plug | D40: Balancing item = Total Assets less all other liabilities & equity, so the Balance Sheet ties out exactly each forecast year

Sheet HDFC CF Forecasting
B1: HDFC Bank Limited
B3: Cash Flow Forecast (2024-2029)
B4: INR ( Rupees in Crores)
B5: Line Items | C5: 2024 | D5: 2025 | E5: 2026 | F5: 2027 | G5: 2028 | H5: 2029
B7: Cash Flow From Operating Activites
B8: Net Profit/(Loss) before taxes (including share in profit from associates and net of minority interest) | C8: ='HDFC IS'!C21+'HDFC IS'!C18+'HDFC IS'!C20-345.38 -> 75184.14 | D8: ='HDFC IS'!D21+'HDFC IS'!D18+'HDFC IS'!D20-976.74 -> 93594.13 | E8: ='HDFC IS'!E21+'HDFC IS'!E18+'HDFC IS'!E20-768.9 -> 98947.96 | F8: ='HDFC IS Forecasting'!F17+'HDFC IS Forecasting'!F20 -> 119995.74 | G8: ='HDFC IS Forecasting'!G17+'HDFC IS Forecasting'!G20 -> 135689.78 | H8: ='HDFC IS Forecasting'!H17+'HDFC IS Forecasting'!H20 -> 153385.8
B9: Depreciation on Fixed Assets | C9: 3092.08 | D9: 3805.23 | E9: 4194.9 | F9: =E9*(1+$C$37) -> 4893.4377 | G9: =F9*(1+$C$37) -> 5708.2965 | H9: =G9*(1+$C$37) -> 6658.8461
B10: Other Operating Activities | C10: 13342.18 | D10: 20242.8 | E10: 30402.47 | F10: =$C$38*'HDFC IS Forecasting'!F11 -> 25267.66 | G10: =$C$38*'HDFC IS Forecasting'!G11 -> 27943.277 | H10: =$C$38*'HDFC IS Forecasting'!H11 -> 30906.942
B11: Tax refund / (Taxes paid) | C11: -22842.84 | D11: 29308.36 | E11: -22656.37 | F11: =E11*(1+$C$39) -> 23291.632 | G11: =F11*(1+$C$39) -> -23944.706 | H11: =G11*(1+$C$39) -> 24616.092
B12: Change in Net Working Capital | C12: -49706.22 | D12: -19708.68 | E12: 2617.42 | F12: =$C$40*'HDFC BS Forecasting'!F21 -> -28476.546 | G12: =$C$40*'HDFC BS Forecasting'!G21 -> -31026.279 | H12: =$C$40*'HDFC BS Forecasting'!H21 -> -33804.309
B14: Total Cash Flow From Operating Activites | C14: =C8+C9+C1+C10+C11+C12 -> 19069.34 | D14: =D8+D9+D1+D10+D11+D12 -> 127241.84 | E14: =E8+E9+E1+E10+E11+E12 -> 113506.38 | F14: =SUM(F8:F12) -> 144971.93 | G14: =SUM(G8:G12) -> 114370.37 | H14: =SUM(H8:H12) -> 181763.37
B16: Cash Flow From Investing Activites
B17: Purchase of Investments | C17: - | D17: - | E17: - | F17: - | G17: - | H17: -
B18: Sale Of Investments | C18: 9500.67 | D18: 192 | E18: 9806 | F18: =E18*(1+$C$41) -> 11074.798 | G18: =F18*(1+$C$41) -> 12507.767 | H18: =G18*(1+$C$41) -> 14126.147
B19: Purchase and Sale of Fixed Assets | C19: -4186.9 | D19: -3975.17 | E19: -3362.41 | F19: =-$C$42*'HDFC BS Forecasting'!E22 -> -4417.8226 | G19: =-$C$42*'SBI BS Forecasting'!F22 -> -16203.309 | H19: =-$C$42*'SBI BS Forecasting'!G22 -> -17053.925
B20: Income from Investments in Associates | C20: - | D20: -67.47 | E20: -80.87 | F20: =$C$43 -> -80.87 | G20: =$C$43 -> -80.87 | H20: =$C$43 -> -80.87
B21: Total Cash Flow From Investing Activites | C21: =SUM(C17:C20) -> 5313.77 | D21: =SUM(D17:D20) -> -3850.64 | E21: =SUM(E17:E20) -> 6362.72 | F21: =SUM(F17:F20) -> 6576.1058 | G21: =SUM(G17:G20) -> -3776.4123 | H21: =SUM(H17:H20) -> -3008.6485
B23: Cash Flow From Financing Activites
B24: Dividend paid | C24: -8404.42 | D24: -14826.19 | E24: -20705.98 | F24: =-$C$44*'HDFC IS Forecasting'!F21 -> -18632.633 | G24: =-$C$44*'HDFC IS Forecasting'!G21 -> -21122.772 | H24: =-$C$44*'HDFC IS Forecasting'!H21 -> -23934.95
B25: Other Financing Activities | C25: 4421.36 | D25: -87651.35 | E25: -38298.87 | F25: =E25*(1+$C$45) -> -42451.607 | G25: =F25*(1+$C$45) -> -47054.624 | H25: =G25*(1+$C$45) -> -52156.744
B26: Total Cash Flow From Financing Activites | C26: =SUM(C24:C25) -> -3983.06 | D26: =SUM(D24:D25) -> -102477.54 | E26: =SUM(E24:E25) -> -59004.85 | F26: =SUM(F24:F25) -> -61084.24 | G26: =SUM(G24:G25) -> -68177.395 | H26: =SUM(H24:H25) -> -76091.694
B28: Effect of fluctuation in foreign currency translation reserve | C28: 104.94 | D28: 199.73 | E28: 1113.9 | F28: =$C$46 -> 1113.9 | G28: =$C$46 -> 1113.9 | H28: =$C$46 -> 1113.9
B29: Net Change in Cash | C29: =C14+C21+C26+C28 -> 20504.99 | D29: =D14+D21+D26+D28 -> 21113.39 | E29: =E14+E21+E26+E28 -> 61978.15 | F29: =F14+F21+F26+F28 -> 91577.694 | G29: =G14+G21+G26+G28 -> 43530.464 | H29: =H14+H21+H26+H28 -> 103776.93
B31: Cash and cash equivalents at the beginning of the year | C31: 208329.52 | D31: ='HDFC BS'!C18+'HDFC BS'!C19 -> 228834.51 | E31: ='HDFC BS'!D18+'HDFC BS'!D19 -> 249947.9 | F31: ='HDFC BS Forecasting'!E18+'HDFC BS Forecasting'!E19 -> 311926.05 | G31: ='HDFC BS Forecasting'!F18+'HDFC BS Forecasting'!F19 -> 403503.74 | H31: ='HDFC BS Forecasting'!G18+'HDFC BS Forecasting'!G19 -> 447034.21
B32: Cash and cash equivalents at the end of the year | C32: =C29+C31 -> 228834.51 | D32: =D31+D29 -> 249947.9 | E32: =E31+E29 -> 311926.05 | F32: =F31+F29 -> 403503.74 | G32: =G31+G29 -> 447034.21 | H32: =H31+H29 -> 550811.14
B35: Key Forecast Assumptions (applied 2027-2029)
B36: Driver / Assumption | C36: Value | D36: Basis / Note
B37: Depreciation growth | C37: =AVERAGE(D9/C9-1,E9/D9-1) -> 0.16652071 | D37: Formula: avg YoY growth, FY2024-FY2026 (row 9)
B38: Other Operating Activities (% of Net Revenue) | C38: =AVERAGE(C10/'HDFC IS Forecasting'!C11,D10/'HDFC IS Forecasting'!D11,E10/'HDFC IS Forecasting'!E11) -> 0.073722186 | D38: Formula: AVERAGE of ratio to 'SBI IS Forecasting' Net Revenue (row 11) each year, FY2024-FY2026
B39: Tax paid growth | C39: =AVERAGE(D11/C11-1,E11/D11-1) -> -2.028039 | D39: Formula: avg YoY growth, FY2024-FY2026 (row 11)
B40: Change in NWC (% of Advances) | C40: =AVERAGE(C12/'HDFC BS Forecasting'!C21,D12/'HDFC BS Forecasting'!D21,E12/'HDFC BS Forecasting'!E21) -> -0.0085670951 | D40: Formula: AVERAGE of ratio to 'SBI BS Forecasting' Advances (row 21) each year, FY2024-FY2026
B41: Purchase/Sale of Investments growth | C41: ='HDFC BS Forecasting'!$C$36 -> 0.12939001 | D41: Formula: linked directly to 'HDFC BS Forecasting' Investments growth assumption for consistency
B42: Capex (% of prior-year Fixed Assets) | C42: =AVERAGE(-D19/'HDFC BS Forecasting'!C22,-E19/'HDFC BS Forecasting'!D22) -> 0.26788336 | D42: Formula: AVERAGE of (Purchase of FA / prior-year Fixed Assets) for FY2025 and FY2026
B43: Income from Investments in Associates (Rs Cr, flat p.a.) | C43: =E20 -> -80.87 | D43: Formula: =E20, i.e. held flat at FY2026 actual (small, historically too volatile to extrapolate)
B44: Dividend payout ratio (% of Net Profit) | C44: =AVERAGE(-C24/'HDFC IS Forecasting'!C21,-D24/'HDFC IS Forecasting'!D21,-E24/'HDFC IS Forecasting'!E21) -> 0.20432611 | D44: Formula: AVERAGE of (-Dividend paid / Net Profit) each year, referencing 'SBI IS Forecasting'
B45: Other Financing Activities growth | C45: =AVERAGE('SBI BS Forecasting'!$C$33,'SBI BS Forecasting'!$C$34) -> 0.10842974 | D45: Formula: AVERAGE of 'SBI BS Forecasting' Deposits growth and Borrowings growth assumptions (normalizes an otherwise extreme, small-base historical growth rate)
B46: FX Translation Effect (Rs Cr, flat p.a.) | C46: =E28 -> 1113.9 | D46: Formula: =E28, i.e. held flat at FY2026 actual (inherently unpredictable currency effect)

Sheet Horizontal Analysis
B1: State Bank Of India | E1: VS | G1: HDFC Bank Limited
B3: Income Statement Growth Horizontal | G3: Income Statement Growth Horizontal
B4: INR ( Rupees in Crores) | G4: INR ( Rupees in Crores) | K4: While both banks delivered approximately 7.4% net profit growth in 2026, HDFC showed stronger operating efficiency,
B5: Line Items | C5: 2025 | D5: 2026 | G5: Line Items | H5: 2025 | I5: 2026 | K5: whereas SBI benefited from normalization in provisions and stronger other-income growth.
B7: Interest Earned | C7: =('SBI IS'!D7-'SBI IS'!C7)/'SBI IS'!C7 -> 0.11640602 | D7: =('SBI IS'!E7-'SBI IS'!D7)/'SBI IS'!D7 -> 0.050212633 | G7: Interest Earned | H7: =('HDFC IS'!D7-'HDFC IS'!C7)/'HDFC IS'!C7 -> 0.1858579 | I7: =('HDFC IS'!E7-'HDFC IS'!D7)/'HDFC IS'!D7 -> 0.03641173 | K7: Both banks experienced slower interest-income growth in 2026, with SBI at 5.02% versus HDFC's 3.64%, indicating a smaller slowdown for SBI.
B8: Interest Expense | C8: =('SBI IS'!D8-'SBI IS'!C8)/'SBI IS'!C8 -> 0.15865063 | D8: =('SBI IS'!E8-'SBI IS'!D8)/'SBI IS'!D8 -> 0.046724654 | G8: Interest Expense | H8: =('HDFC IS'!D8-'HDFC IS'!C8)/'HDFC IS'!C8 -> 0.19304483 | I8: =('HDFC IS'!E8-'HDFC IS'!D8)/'HDFC IS'!D8 -> 0.0086845045 | K8: Interest expense growth declined for both banks, but HDFC improved more sharply to 0.87% versus SBI's 4.67%, indicating better expense control.
B9: Net Interest Income | C9: =('SBI IS'!D9-'SBI IS'!C9)/'SBI IS'!C9 -> 0.055261985 | D9: =('SBI IS'!E9-'SBI IS'!D9)/'SBI IS'!D9 -> 0.055755684 | G9: Net Interest Income | H9: =('HDFC IS'!D9-'HDFC IS'!C9)/'HDFC IS'!C9 -> 0.17730428 | I9: =('HDFC IS'!E9-'HDFC IS'!D9)/'HDFC IS'!D9 -> 0.069852852 | K9: HDFC maintained significantly stronger NII growth at 6.99%, while SBI remained stable at 5.58%.
B10: Other Income | C10: =('SBI IS'!D10-'SBI IS'!C10)/'SBI IS'!C10 -> 0.11355065 | D10: =('SBI IS'!E10-'SBI IS'!D10)/'SBI IS'!D10 -> 0.14263556 | G10: Other Income | H10: =('HDFC IS'!D10-'HDFC IS'!C10)/'HDFC IS'!C10 -> 0.082051457 | I10: =('HDFC IS'!E10-'HDFC IS'!D10)/'HDFC IS'!D10 -> 0.091410607 | K10: SBI outperformed HDFC in other-income growth at 14.26% versus 9.14%, providing stronger non-interest income support.
B11: Net Revenue | C11: =('SBI IS'!D11-'SBI IS'!C11)/'SBI IS'!C11 -> 0.082311611 | D11: =('SBI IS'!E11-'SBI IS'!D11)/'SBI IS'!D11 -> 0.097237141 | G11: Net Revenue | H11: =('HDFC IS'!D11-'HDFC IS'!C11)/'HDFC IS'!C11 -> 0.13064683 | I11: =('HDFC IS'!E11-'HDFC IS'!D11)/'HDFC IS'!D11 -> 0.07995858 | K11: SBI's revenue growth accelerated to 9.72%, while HDFC's slowed to 8.00%, giving SBI the stronger 2026 growth trend.
B13: Operating expenses | C13: =('SBI IS'!D13-'SBI IS'!C13)/'SBI IS'!C13 -> 0.0028812953 | D13: =('SBI IS'!E13-'SBI IS'!D13)/'SBI IS'!D13 -> 0.11022759 | G13: Operating expenses | H13: =('HDFC IS'!D13-'HDFC IS'!C13)/'HDFC IS'!C13 -> 0.15982029 | I13: =('HDFC IS'!E13-'HDFC IS'!D13)/'HDFC IS'!D13 -> 0.025870378 | K13: HDFC showed substantially better expense control, with growth slowing to 2.59% compared with SBI's sharp increase to 11.02%.
B14: Operating Income | C14: =('SBI IS'!D14-'SBI IS'!C14)/'SBI IS'!C14 -> 0.27168064 | D14: =('SBI IS'!E14-'SBI IS'!D14)/'SBI IS'!D14 -> 0.072813047 | G14: Operating Income | H14: =('HDFC IS'!D14-'HDFC IS'!C14)/'HDFC IS'!C14 -> 0.086918508 | I14: =('HDFC IS'!E14-'HDFC IS'!D14)/'HDFC IS'!D14 -> 0.16646953 | K14: HDFC significantly outperformed SBI, with operating income growth accelerating to 16.65% versus SBI's 7.28%.
B16: Provisions and contingencies (ex-tax) | C16: =('SBI IS'!D16-'SBI IS'!C16)/'SBI IS'!C16 -> 1.5257911 | D16: =('SBI IS'!E16-'SBI IS'!D16)/'SBI IS'!D16 -> 0.07703134 | G16: Provisions and contingencies (ex-tax) | H16: =('HDFC IS'!D16-'HDFC IS'!C16)/'HDFC IS'!C16 -> -0.39188813 | I16: =('HDFC IS'!E16-'HDFC IS'!D16)/'HDFC IS'!D16 -> 0.83523889 | K16: SBI's provision growth normalized sharply to 7.70%, whereas HDFC experienced a significant increase to 83.52%, creating greater earnings pressure.
B17: Net Profit Before Taxation | C17: =('SBI IS'!D17-'SBI IS'!C17)/'SBI IS'!C17 -> 0.16577433 | D17: =('SBI IS'!E17-'SBI IS'!D17)/'SBI IS'!D17 -> 0.072041245 | G17: Net Profit Before Taxation | H17: =('HDFC IS'!D17-'HDFC IS'!C17)/'HDFC IS'!C17 -> 0.25210474 | I17: =('HDFC IS'!E17-'HDFC IS'!D17)/'HDFC IS'!D17 -> 0.054414113 | K17: SBI recorded stronger PBT growth at 7.20% compared with HDFC's 5.44%, despite HDFC's stronger operating-income growth.
B18: Taxation | C18: =('SBI IS'!D18-'SBI IS'!C18)/'SBI IS'!C18 -> 0.18381094 | D18: =('SBI IS'!E18-'SBI IS'!D18)/'SBI IS'!D18 -> 0.055264087 | G18: Taxation | H18: =('HDFC IS'!D18-'HDFC IS'!C18)/'HDFC IS'!C18 -> 1.0956717 | I18: =('HDFC IS'!E18-'HDFC IS'!D18)/'HDFC IS'!D18 -> -0.029970611 | K18: SBI's tax expense increased 5.53%, while HDFC's declined 3.00%, indicating lower tax-expense growth for HDFC.
B19: Net Profit After taxation | C19: =('SBI IS'!D19-'SBI IS'!C19)/'SBI IS'!C19 -> 0.15965914 | D19: =('SBI IS'!E19-'SBI IS'!D19)/'SBI IS'!D19 -> 0.077847884 | G19: Net Profit After taxation | H19: =('HDFC IS'!D19-'HDFC IS'!C19)/'HDFC IS'!C19 -> 0.12214053 | I19: =('HDFC IS'!E19-'HDFC IS'!D19)/'HDFC IS'!D19 -> 0.078693854 | K19: Both banks delivered similar PAT growth of around 7.8%, with HDFC marginally ahead at 7.87% versus SBI's 7.78%.
B20: Share in Profit of Associates | C20: =('SBI IS'!D20-'SBI IS'!C20)/'SBI IS'!C20 -> 0.071391875 | D20: =('SBI IS'!E20-'SBI IS'!D20)/'SBI IS'!D20 -> -0.0054945599 | G20: Share in Profit of Associates | H20: =('HDFC IS'!D20-'HDFC IS'!C20)/'HDFC IS'!C20 -> 0.9126013 | I20: =('HDFC IS'!E20-'HDFC IS'!D20)/'HDFC IS'!D20 -> 0.20603719 | K20: HDFC recorded strong 20.60% growth in associate profits, while SBI reported a 0.55% decline, favoring HDFC.
B21: Less: Minority Interest | C21: =('SBI IS'!D21-'SBI IS'!C21)/'SBI IS'!C21 -> 0.20438812 | D21: =('SBI IS'!E21-'SBI IS'!D21)/'SBI IS'!D21 -> 0.13696641 | G21: Less: Minority Interest | H21: =('HDFC IS'!D21-'HDFC IS'!C21)/'HDFC IS'!C21 -> 0.10505769 | I21: =('HDFC IS'!E21-'HDFC IS'!D21)/'HDFC IS'!D21 -> 0.073930692 | K21: Minority interest grew faster at SBI (13.70%) than HDFC (7.39%), resulting in relatively greater deduction pressure for SBI.
B22: Net Profit | C22: =('SBI IS'!D22-'SBI IS'!C22)/'SBI IS'!C22 -> 0.15617092 | D22: =('SBI IS'!E22-'SBI IS'!D22)/'SBI IS'!D22 -> 0.073973059 | G22: Net Profit | H22: =('HDFC IS'!D21-'HDFC IS'!C21)/'HDFC IS'!C21 -> 0.10505769 | I22: =('HDFC IS'!E21-'HDFC IS'!D21)/'HDFC IS'!D21 -> 0.073930692 | K22: Both banks delivered almost identical net-profit growth of approximately 7.4%, indicating broadly similar bottom-line performance in 2026.
B26: State Bank Of India | G26: HDFC Bank Limited
B28: Balance Sheet Growth Horizontal | G28: Balance Sheet Growth Horizontal
B29: INR ( Rupees in Crores) | G29: INR ( Rupees in Crores) | K29: SBI expanded its balance sheet faster, driven particularly by advances and borrowings,
B30: Line Items | C30: 2025 | D30: 2026 | G30: Line Items | H30: 2025 | I30: 2026 | K30: while HDFC showed stronger deposit, capital and liquidity growth with lower borrowing dependence.
B32: Capital and Liabilities | G32: Capital and Liabilities
B33: Capital | C33: =('SBI BS'!D8-'SBI BS'!C8)/'SBI BS'!C8 -> 8.9639751e-07 | D33: =('SBI BS'!E8-'SBI BS'!D8)/'SBI BS'!D8 -> 0.03428695 | G33: Capital | H33: =('HDFC BS'!D8-'HDFC BS'!C8)/'HDFC BS'!C8 -> 0.007279285 | I33: =('HDFC BS'!E8-'HDFC BS'!D8)/'HDFC BS'!D8 -> 1.0116306 | K33: HDFC's capital growth surged to 101.16%, significantly above SBI's 3.43%, indicating a major increase in HDFC's capital base.
B34: Reserves & Surplus | C34: =('SBI BS'!D9-'SBI BS'!C9)/'SBI BS'!C9 -> 0.17412911 | D34: =('SBI BS'!E9-'SBI BS'!D9)/'SBI BS'!D9 -> 0.22434391 | G34: Reserves & Surplus | H34: =('HDFC BS'!D9-'HDFC BS'!C9)/'HDFC BS'!C9 -> 0.14180701 | I34: =('HDFC BS'!E9-'HDFC BS'!D9)/'HDFC BS'!D9 -> 0.1213336 | K34: SBI recorded stronger growth in reserves and surplus at 22.43% compared with HDFC's 12.13%, indicating greater internal capital accumulation.
B35: Minority Interest & Other Equity | C35: =('SBI BS'!D10-'SBI BS'!C10)/'SBI BS'!C10 -> 0.15417353 | D35: =('SBI BS'!E10-'SBI BS'!D10)/'SBI BS'!D10 -> 0.041187737 | G35: Minority Interest & Other Equity | H35: =('HDFC BS'!D10-'HDFC BS'!C10)/'HDFC BS'!C10 -> 0.25742574 | I35: =('HDFC BS'!E10-'HDFC BS'!D10)/'HDFC BS'!D10 -> 0.33553674 | K35: HDFC's minority interest and other equity grew 33.55%, substantially faster than SBI's 4.12%.
B37: Deposits | C37: =('SBI BS'!D12-'SBI BS'!C12)/'SBI BS'!C12 -> 0.095309969 | D37: =('SBI BS'!E12-'SBI BS'!D12)/'SBI BS'!D12 -> 0.11088427 | G37: Deposits | H37: =('HDFC BS'!D12-'HDFC BS'!C12)/'HDFC BS'!C12 -> 0.14052452 | I37: =('HDFC BS'!E12-'HDFC BS'!D12)/'HDFC BS'!D12 -> 0.14339899 | K37: HDFC's deposits grew faster at 14.34% versus SBI's 11.09%, indicating stronger deposit expansion.
B38: Borrowings | C38: =('SBI BS'!D13-'SBI BS'!C13)/'SBI BS'!C13 -> -0.044952831 | D38: =('SBI BS'!E13-'SBI BS'!D13)/'SBI BS'!D13 -> 0.27247757 | G38: Borrowings | H38: =('HDFC BS'!D13-'HDFC BS'!C13)/'HDFC BS'!C13 -> -0.13140961 | I38: =('HDFC BS'!E13-'HDFC BS'!D13)/'HDFC BS'!D13 -> -0.072676671 | K38: SBI's borrowings increased 27.25%, while HDFC's declined 7.27%, indicating greater reliance on borrowings for SBI.
B39: Other Liabilities and Provisions | C39: =('SBI BS'!D14-'SBI BS'!C14)/'SBI BS'!C14 -> 0.087928605 | D39: =('SBI BS'!E14-'SBI BS'!D14)/'SBI BS'!D14 -> 0.16865527 | G39: Other Liabilities and Provisions | H39: =('HDFC BS'!D14-'HDFC BS'!C14)/'HDFC BS'!C14 -> 0.12331802 | I39: =('HDFC BS'!E14-'HDFC BS'!D14)/'HDFC BS'!D14 -> 0.20187777 | K39: SBI recorded stronger growth of 16.87% versus HDFC's 12.33%, reflecting a larger increase in other liabilities and provisions.
B40: Total Capital and Liabilities | C40: =('SBI BS'!D15-'SBI BS'!C15)/'SBI BS'!C15 -> 0.086193289 | D40: =('SBI BS'!E15-'SBI BS'!D15)/'SBI BS'!D15 -> 0.13773007 | G40: Total Capital and Liabilities | H40: =('HDFC BS'!D15-'HDFC BS'!C15)/'HDFC BS'!C15 -> 0.089877345 | I40: =('HDFC BS'!E15-'HDFC BS'!D15)/'HDFC BS'!D15 -> 0.11738944 | K40: SBI's total capital and liabilities grew 13.77%, outperforming HDFC's 11.74%, indicating faster overall balance-sheet expansion.
B42: Assets | G42: Assets
B43: Cash and Balances with Reserve Bank of India | C43: =('SBI BS'!D18-'SBI BS'!C18)/'SBI BS'!C18 -> 0.0094464653 | D43: =('SBI BS'!E18-'SBI BS'!D18)/'SBI BS'!D18 -> 0.18109568 | G43: Cash and Balances with Reserve Bank of India | H43: =('HDFC BS'!D18-'HDFC BS'!C18)/'HDFC BS'!C18 -> -0.19208077 | I43: =('HDFC BS'!E18-'HDFC BS'!D18)/'HDFC BS'!D18 -> 0.39003229 | K43: HDFC's cash and RBI balances increased 39.00%, significantly above SBI's 18.11%, indicating stronger liquidity accumulation.
B44: Balances with Banks and Money at Call & Short Notice | C44: =('SBI BS'!D19-'SBI BS'!C19)/'SBI BS'!C19 -> 0.28880639 | D44: =('SBI BS'!E19-'SBI BS'!D19)/'SBI BS'!D19 -> 0.020802857 | G44: Balances with Banks and Money at Call & Short Notice | H44: =('HDFC BS'!D19-'HDFC BS'!C19)/'HDFC BS'!C19 -> 1.1062732 | I44: =('HDFC BS'!E19-'HDFC BS'!D19)/'HDFC BS'!D19 -> 0.05363221 | K44: SBI's growth slowed sharply to 2.08%, while HDFC grew 5.36%, indicating slightly stronger short-term banking liquidity growth at HDFC.
B45: Investments | C45: =('SBI BS'!D20-'SBI BS'!C20)/'SBI BS'!C20 -> 0.045037058 | D45: =('SBI BS'!E20-'SBI BS'!D20)/'SBI BS'!D20 -> 0.069777378 | G45: Investments | H45: =('HDFC BS'!D20-'HDFC BS'!C20)/'HDFC BS'!C20 -> 0.17976987 | I45: =('HDFC BS'!E20-'HDFC BS'!D20)/'HDFC BS'!D20 -> 0.079010149 | K45: Investment growth remained relatively strong at both banks, with HDFC at 7.90% compared with SBI's 6.98%.
B46: Advances | C46: =('SBI BS'!D21-'SBI BS'!C21)/'SBI BS'!C21 -> 0.1232887 | D46: =('SBI BS'!E21-'SBI BS'!D21)/'SBI BS'!D21 -> 0.17106832 | G46: Advances | H46: =('HDFC BS'!D21-'HDFC BS'!C21)/'HDFC BS'!C21 -> 0.059497072 | I46: =('HDFC BS'!E21-'HDFC BS'!D21)/'HDFC BS'!D21 -> 0.11957889 | K46: SBI's advances grew faster at 17.11% versus HDFC's 11.96%, indicating stronger loan-book expansion at SBI.
B47: Fixed Assets | C47: =('SBI BS'!D22-'SBI BS'!C22)/'SBI BS'!C22 -> 0.036447876 | D47: =('SBI BS'!E22-'SBI BS'!D22)/'SBI BS'!D22 -> 0.23338247 | G47: Fixed Assets | H47: =('HDFC BS'!D22-'HDFC BS'!C22)/'HDFC BS'!C22 -> 0.21058636 | I47: =('HDFC BS'!E22-'HDFC BS'!D22)/'HDFC BS'!D22 -> 0.080852985 | K47: SBI's fixed assets increased 23.34%, substantially faster than HDFC's 8.09%, indicating greater expansion in its fixed-asset base.
B48: Other Assets | C48: =('SBI BS'!D23-'SBI BS'!C23)/'SBI BS'!C23 -> -0.030351186 | D48: =('SBI BS'!E23-'SBI BS'!D23)/'SBI BS'!D23 -> 0.15783403 | G48: Other Assets | H48: =('HDFC BS'!D23-'HDFC BS'!C23)/'HDFC BS'!C23 -> 0.021987452 | I48: =('HDFC BS'!E23-'HDFC BS'!D23)/'HDFC BS'!D23 -> 0.15209949 | K48: SBI's other assets grew 15.78%, slightly above HDFC's 15.21%, indicating broadly similar expansion.
B49: Total Assets | C49: =('SBI BS'!D24-'SBI BS'!C24)/'SBI BS'!C24 -> 0.086193289 | D49: =('SBI BS'!E24-'SBI BS'!D24)/'SBI BS'!D24 -> 0.13773007 | G49: Total Assets | H49: =('HDFC BS'!D24-'HDFC BS'!C24)/'HDFC BS'!C24 -> 0.089877345 | I49: =('HDFC BS'!E24-'HDFC BS'!D24)/'HDFC BS'!D24 -> 0.11738944 | K49: SBI's total assets grew 13.77% versus HDFC's 11.74%, indicating faster overall asset growth at SBI.
B53: State Bank Of India | G53: HDFC Bank Limited
B55: Cash Flow Growth Horizontal | G55: Cash Flow Growth Horizontal
B56: INR ( Rupees in Crores) | G56: INR ( Rupees in Crores) | K56: HDFC demonstrated stronger cash accumulation in 2026, with a smaller decline in operating cash flow and significantly higher ending cash growth,
B57: Line Items | C57: 2025 | D57: 2026 | G57: Line Items | H57: 2025 | I57: 2026 | K57: while SBI experienced greater pressure from investing and financing cash flows.
B59: Cash Flow From Operating Activites | G59: Cash Flow From Operating Activites
B60: Net Profit/(Loss) before taxes (including share in profit from associates and net of minority interest) | C60: =('SBI CF'!D8-'SBI CF'!C8)/'SBI CF'!C8 -> 0.16325107 | D60: =('SBI CF'!E8-'SBI CF'!D8)/'SBI CF'!D8 -> 0.069095944 | G60: Net Profit/(Loss) before taxes (including share in profit from associates and net of minority interest) | H60: =('HDFC CF'!D8-'HDFC CF'!C8)/'HDFC CF'!C8 -> 0.24486534 | I60: =('HDFC CF'!E8-'HDFC CF'!D8)/'HDFC CF'!D8 -> 0.057202626 | K60: PBT growth slowed at both banks, with SBI at 6.91% and HDFC at 5.72%, although SBI maintained slightly stronger growth.
B61: Depreciation on Fixed Assets | C61: =('SBI CF'!D9-'SBI CF'!C9)/'SBI CF'!C9 -> 0.036983007 | D61: =('SBI CF'!E9-'SBI CF'!D9)/'SBI CF'!D9 -> 0.21000794 | G61: Depreciation on Fixed Assets | H61: =('HDFC CF'!D9-'HDFC CF'!C9)/'HDFC CF'!C9 -> 0.23063763 | I61: =('HDFC CF'!E9-'HDFC CF'!D9)/'HDFC CF'!D9 -> 0.1024038 | K61: SBI's depreciation growth accelerated to 21.00%, double HDFC's 10.24%, indicating a larger increase in depreciation expense at SBI.
B62: Other Operating Activities | C62: =('SBI CF'!D10-'SBI CF'!C10)/'SBI CF'!C10 -> 0.83620125 | D62: =('SBI CF'!E10-'SBI CF'!D10)/'SBI CF'!D10 -> 0.41912936 | G62: Other Operating Activities | H62: =('HDFC CF'!D10-'HDFC CF'!C10)/'HDFC CF'!C10 -> 0.51720334 | I62: =('HDFC CF'!E10-'HDFC CF'!D10)/'HDFC CF'!D10 -> 0.50189055 | K62: Other operating adjustments increased significantly at both banks, with HDFC at 50.19% versus SBI's 41.91%.
B63: Tax refund / (Taxes paid) | C63: =('SBI CF'!D11-'SBI CF'!C11)/'SBI CF'!C11 -> 0.079735049 | D63: =('SBI CF'!E11-'SBI CF'!D11)/'SBI CF'!D11 -> 0.075871195 | G63: Tax refund / (Taxes paid) | H63: =('HDFC CF'!D11-'HDFC CF'!C11)/'HDFC CF'!C11 -> -2.2830436 | I63: =('HDFC CF'!E11-'HDFC CF'!D11)/'HDFC CF'!D11 -> -1.7730344 | K63: Tax-related cash outflows showed relatively stable growth at SBI, while HDFC's large negative growth reflects a substantial change in tax cash flows and should be interpreted cautiously.
B64: Change in Net Working Capital | C64: =('SBI CF'!D12-'SBI CF'!C12)/'SBI CF'!C12 -> -0.042268939 | D64: =('SBI CF'!E12-'SBI CF'!D12)/'SBI CF'!D12 -> 0.42877972 | G64: Change in Net Working Capital | H64: =('HDFC CF'!D12-'HDFC CF'!C12)/'HDFC CF'!C12 -> -0.60349671 | I64: =('HDFC CF'!E12-'HDFC CF'!D12)/'HDFC CF'!D12 -> -1.1328054 | K64: SBI moved to a 42.88% increase in the working-capital adjustment, while HDFC recorded a much larger negative movement of 113.28%, indicating significantly different operating cash-flow effects.
B66: Total Cash Flow From Operating Activites | C66: =('SBI CF'!D14-'SBI CF'!C14)/'SBI CF'!C14 -> 1.1025847 | D66: =('SBI CF'!E14-'SBI CF'!D14)/'SBI CF'!D14 -> -0.16240037 | G66: Total Cash Flow From Operating Activites | H66: =('HDFC CF'!D14-'HDFC CF'!C14)/'HDFC CF'!C14 -> 5.6725875 | I66: =('HDFC CF'!E14-'HDFC CF'!D14)/'HDFC CF'!D14 -> -0.10794767 | K66: Operating cash flow declined for both banks in 2026, but SBI's 16.24% decline was greater than HDFC's 10.79% decline.
B68: Cash Flow From Investing Activites | G68: Cash Flow From Investing Activites
B69: Purchase of Investments | C69: - | D69: - | G69: Purchase of Investments | H69: - | I69: - | K69: No meaningful year-on-year growth is reported for investment purchases for either bank, indicating no significant comparable movement in this line.
B70: Sale Of Investments | C70: - | D70: =('SBI CF'!E18-'SBI CF'!D18)/'SBI CF'!D18 -> -1194.3442 | G70: Sale Of Investments | H70: =('HDFC CF'!D18-'HDFC CF'!C18)/'HDFC CF'!C18 -> -0.9797909 | I70: =('HDFC CF'!E18-'HDFC CF'!D18)/'HDFC CF'!D18 -> 50.072917 | K70: Both banks experienced exceptionally large changes in investment-sale cash flows; however, the percentages are heavily distorted by the prior-year base and should be interpreted as major cash-flow swings.
B71: Purchase of Fixed Assets | C71: =('SBI CF'!D19-'SBI CF'!C19)/'SBI CF'!C19 -> 0.3501925 | D71: =('SBI CF'!E19-'SBI CF'!D19)/'SBI CF'!D19 -> 0.48352417 | G71: Purchase of Fixed Assets | H71: =('HDFC CF'!D19-'HDFC CF'!C19)/'HDFC CF'!C19 -> -0.050569634 | I71: =('HDFC CF'!E19-'HDFC CF'!D19)/'HDFC CF'!D19 -> -0.15414687 | K71: SBI's fixed-asset purchases increased sharply by 48.35%, while HDFC's declined 15.41%, indicating substantially higher investment spending by SBI.
B72: Income from Investments in Associates | C72: =('SBI CF'!D20-'SBI CF'!C20)/'SBI CF'!C20 -> 0.61540947 | D72: =('SBI CF'!E20-'SBI CF'!D20)/'SBI CF'!D20 -> -0.89668811 | G72: Income from Investments in Associates | H72: - | I72: =('HDFC CF'!E20-'HDFC CF'!D20)/'HDFC CF'!D20 -> 0.19860679 | K72: SBI's income from associates declined 89.67%, while HDFC recorded 19.86% growth, indicating significantly stronger associate-income performance at HDFC.
B73: Total Cash Flow From Investing Activites | C73: =('SBI CF'!D21-'SBI CF'!C21)/'SBI CF'!C21 -> 0.32528681 | D73: =('SBI CF'!E21-'SBI CF'!D21)/'SBI CF'!D21 -> -0.87738823 | G73: Total Cash Flow From Investing Activites | H73: =('HDFC CF'!D21-'HDFC CF'!C21)/'HDFC CF'!C21 -> -1.7246531 | I73: =('HDFC CF'!E21-'HDFC CF'!D21)/'HDFC CF'!D21 -> -2.6523799 | K73: Investing cash flow declined sharply for both banks, with SBI at -87.74% and HDFC at -265.24%, although the magnitude is influenced by changes in investment-sale proceeds.
B75: Cash Flow From Financing Activites | G75: Cash Flow From Financing Activites
B76: Dividend paid | C76: =('SBI CF'!D24-'SBI CF'!C24)/'SBI CF'!C24 -> 0.21238937 | D76: =('SBI CF'!E24-'SBI CF'!D24)/'SBI CF'!D24 -> 0.160585 | G76: Dividend paid | H76: =('HDFC CF'!D24-'HDFC CF'!C24)/'HDFC CF'!C24 -> 0.76409437 | I76: =('HDFC CF'!E24-'HDFC CF'!D24)/'HDFC CF'!D24 -> 0.39658132 | K76: Dividend payments increased at both banks, with HDFC's growth of 39.66% significantly exceeding SBI's 16.06%.
B77: Other Financing Activities | C77: =('SBI CF'!D25-'SBI CF'!C25)/'SBI CF'!C25 -> 6.9028499 | D77: =('SBI CF'!E25-'SBI CF'!D25)/'SBI CF'!D25 -> 6.2238626 | G77: Other Financing Activities | H77: =('HDFC CF'!D25-'HDFC CF'!C25)/'HDFC CF'!C25 -> -20.824522 | I77: =('HDFC CF'!E25-'HDFC CF'!D25)/'HDFC CF'!D25 -> -0.56305442 | K77: SBI recorded a substantial increase of 622.39%, while HDFC's other financing cash flows declined 56.31%, indicating very different financing movements.
B78: Total Cash Flow From Financing Activites | C78: =('SBI CF'!D26-'SBI CF'!C26)/'SBI CF'!C26 -> 0.084932154 | D78: =('SBI CF'!E26-'SBI CF'!D26)/'SBI CF'!D26 -> -0.6808044 | G78: Total Cash Flow From Financing Activites | H78: =('HDFC CF'!D26-'HDFC CF'!C26)/'HDFC CF'!C26 -> 24.728345 | I78: =('HDFC CF'!E26-'HDFC CF'!D26)/'HDFC CF'!D26 -> -0.42421676 | K78: SBI's financing cash flow declined 68.08%, while HDFC declined 42.42%, indicating a larger negative financing impact on SBI's cash flow.
B80: Effect of fluctuation in foreign currency translation reserve | C80: =('SBI CF'!D28-'SBI CF'!C28)/'SBI CF'!C28 -> 1.8972787 | D80: =('SBI CF'!E28-'SBI CF'!D28)/'SBI CF'!D28 -> 3.417332 | G80: Effect of fluctuation in foreign currency translation reserve | H80: =('HDFC CF'!D28-'HDFC CF'!C28)/'HDFC CF'!C28 -> 0.90327806 | I80: =('HDFC CF'!E28-'HDFC CF'!D28)/'HDFC CF'!D28 -> 4.577029 | K80: Foreign-currency translation effects increased substantially for both banks, with HDFC rising 457.70% compared with SBI's 341.73%.
B81: Net Change in Cash | C81: =('SBI CF'!D29-'SBI CF'!C29)/'SBI CF'!C29 -> 2.7965093 | D81: =('SBI CF'!E29-'SBI CF'!D29)/'SBI CF'!D29 -> 0.40017125 | G81: Net Change in Cash | H81: =('HDFC CF'!D29-'HDFC CF'!C29)/'HDFC CF'!C29 -> 0.029670826 | I81: =('HDFC CF'!E29-'HDFC CF'!D29)/'HDFC CF'!D29 -> 1.9354902 | K81: HDFC recorded a significantly stronger increase in net cash of 193.55%, compared with SBI's 40.02%, indicating stronger cash accumulation at HDFC.
B83: Cash and cash equivalents at the beginning of the year | C83: =('SBI CF'!D31-'SBI CF'!C31)/'SBI CF'!C31 -> 0.025950628 | D83: =('SBI CF'!E31-'SBI CF'!D31)/'SBI CF'!D31 -> 0.096029697 | G83: Cash and cash equivalents at the beginning of the year | H83: =('HDFC CF'!D31-'HDFC CF'!C31)/'HDFC CF'!C31 -> 0.098425754 | I83: =('HDFC CF'!E31-'HDFC CF'!D31)/'HDFC CF'!D31 -> 0.092264886 | K83: Beginning cash balances increased at both banks, with SBI growing 9.60% versus HDFC's 9.23%, indicating broadly similar starting liquidity growth.
B84: Cash and cash equivalents at the end of the year | C84: =('SBI CF'!D32-'SBI CF'!C32)/'SBI CF'!C32 -> 0.096029715 | D84: =('SBI CF'!E32-'SBI CF'!D32)/'SBI CF'!D32 -> 0.12267735 | G84: Cash and cash equivalents at the end of the year | H84: =('HDFC CF'!D32-'HDFC CF'!C32)/'HDFC CF'!C32 -> 0.092264886 | I84: =('HDFC CF'!E32-'HDFC CF'!D32)/'HDFC CF'!D32 -> 0.24796428 | K84: HDFC's ending cash and equivalents grew 24.80%, substantially above SBI's 12.27%, indicating stronger year-end liquidity growth at HDFC.

Sheet Vertical Analysis
B1: State Bank Of India | E1: VS | G1: HDFC Bank Limited
B3: Income Statement Growth Horizontal | G3: Income Statement Growth Horizontal
B4: INR ( Rupees in Crores) | G4: INR ( Rupees in Crores) | K4: HDFC demonstrates stronger overall profitability, with higher NII, net revenue, operating income, PBT and net profit relative to interest earned,
B5: Line Items | C5: 2025 | D5: 2026 | G5: Line Items | H5: 2025 | I5: 2026 | K5: while SBI has a lower operating expense burden.
B7: Interest Earned | C7: ='SBI IS'!D7/'SBI IS'!$D$7 -> 1 | D7: ='SBI IS'!E7/'SBI IS'!$E$7 -> 1 | G7: Interest Earned | H7: ='HDFC IS'!D7/'HDFC IS'!$D$7 -> 1 | I7: ='HDFC IS'!E7/'HDFC IS'!$E$7 -> 1 | K7: Base
B8: Interest Expense | C8: ='SBI IS'!D8/'SBI IS'!$D$7 -> 0.61377838 | D8: ='SBI IS'!E8/'SBI IS'!$E$7 -> 0.61173989 | G8: Interest Expense | H8: ='HDFC IS'!D8/'HDFC IS'!$D$7 -> 0.54670632 | I8: ='HDFC IS'!E8/'HDFC IS'!$E$7 -> 0.53208023 | K8: SBI's interest expense was higher at 61.17% versus HDFC's 53.21%, indicating relatively higher funding costs for SBI.
B9: Net Interest Income | C9: ='SBI IS'!D9/'SBI IS'!$D$7 -> 0.38622162 | D9: ='SBI IS'!E9/'SBI IS'!$E$7 -> 0.38826011 | G9: Net Interest Income | H9: ='HDFC IS'!D9/'HDFC IS'!$D$7 -> 0.45329368 | I9: ='HDFC IS'!E9/'HDFC IS'!$E$7 -> 0.46791977 | K9: HDFC generated a higher NII contribution of 46.79% versus SBI's 38.83%, indicating a stronger interest spread.
B10: Other Income | C10: ='SBI IS'!D10/'SBI IS'!$D$7 -> 0.35289851 | D10: ='SBI IS'!E10/'SBI IS'!$E$7 -> 0.38395499 | G10: Other Income | H10: ='HDFC IS'!D10/'HDFC IS'!$D$7 -> 0.40000454 | I10: ='HDFC IS'!E10/'HDFC IS'!$E$7 -> 0.42123144 | K10: HDFC's other income was higher at 42.12% versus SBI's 38.40%, showing greater contribution from non-interest income.
B11: Net Revenue | C11: ='SBI IS'!D11/'SBI IS'!$D$7 -> 0.73912012 | D11: ='SBI IS'!E11/'SBI IS'!$E$7 -> 0.7722151 | G11: Net Revenue | H11: ='HDFC IS'!D11/'HDFC IS'!$D$7 -> 0.85329822 | I11: ='HDFC IS'!E11/'HDFC IS'!$E$7 -> 0.8891512 | K11: HDFC's net revenue represented 88.92% of interest earned versus 77.22% for SBI, indicating stronger revenue generation after interest expense.
B13: Operating expenses | C13: ='SBI IS'!D13/'SBI IS'!$D$7 -> 0.48249519 | D13: ='SBI IS'!E13/'SBI IS'!$E$7 -> 0.51006763 | G13: Operating expenses | H13: ='HDFC IS'!D13/'HDFC IS'!$D$7 -> 0.52503618 | I13: ='HDFC IS'!E13/'HDFC IS'!$E$7 -> 0.51969603 | K13: SBI's operating expenses were marginally lower at 51.01% versus HDFC's 51.97%, though the two banks are now much closer on this measure than in 2025.
B14: Operating Income | C14: ='SBI IS'!D14/'SBI IS'!$D$7 -> 0.25662493 | D14: ='SBI IS'!E14/'SBI IS'!$E$7 -> 0.26214746 | G14: Operating Income | H14: ='HDFC IS'!D14/'HDFC IS'!$D$7 -> 0.32826204 | I14: ='HDFC IS'!E14/'HDFC IS'!$E$7 -> 0.36945517 | K14: HDFC generated significantly higher operating income at 36.95% versus SBI's 26.21%, indicating stronger core operating profitability.
B16: Provisions and contingencies (ex-tax) | C16: ='SBI IS'!D16/'SBI IS'!$D$7 -> 0.039691344 | D16: ='SBI IS'!E16/'SBI IS'!$E$7 -> 0.04070492 | G16: Provisions and contingencies (ex-tax) | H16: ='HDFC IS'!D16/'HDFC IS'!$D$7 -> 0.047108574 | I16: ='HDFC IS'!E16/'HDFC IS'!$E$7 -> 0.08341809 | K16: HDFC's provisions rose sharply to 8.34% versus SBI's 4.07%, indicating a much greater provisioning burden at HDFC in 2026.
B17: Net Profit Before Taxation | C17: ='SBI IS'!D17/'SBI IS'!$D$7 -> 0.21693359 | D17: ='SBI IS'!E17/'SBI IS'!$E$7 -> 0.22144254 | G17: Net Profit Before Taxation | H17: ='HDFC IS'!D17/'HDFC IS'!$D$7 -> 0.28115347 | I17: ='HDFC IS'!E17/'HDFC IS'!$E$7 -> 0.28603708 | K17: HDFC's PBT was significantly higher at 28.60% versus SBI's 22.14%, reflecting stronger pre-tax profitability.
B18: Taxation | C18: ='SBI IS'!D18/'SBI IS'!$D$7 -> 0.055776936 | D18: ='SBI IS'!E18/'SBI IS'!$E$7 -> 0.056045219 | G18: Taxation | H18: ='HDFC IS'!D18/'HDFC IS'!$D$7 -> 0.062820291 | I18: ='HDFC IS'!E18/'HDFC IS'!$E$7 -> 0.058796642 | K18: SBI's and HDFC's tax burdens are now close, at 5.60% and 5.88% of interest earned respectively.
B19: Net Profit After taxation | C19: ='SBI IS'!D19/'SBI IS'!$D$7 -> 0.16115665 | D19: ='SBI IS'!E19/'SBI IS'!$E$7 -> 0.16539732 | G19: Net Profit After taxation | H19: ='HDFC IS'!D19/'HDFC IS'!$D$7 -> 0.21833318 | I19: ='HDFC IS'!E19/'HDFC IS'!$E$7 -> 0.22724044 | K19: HDFC generated 22.72% versus SBI's 16.54%, demonstrating stronger post-tax profitability.
B20: Share in Profit of Associates | C20: ='SBI IS'!D20/'SBI IS'!$D$7 -> 0.0030704302 | D20: ='SBI IS'!E20/'SBI IS'!$E$7 -> 0.0029075631 | G20: Share in Profit of Associates | H20: - | I20: - | K20: SBI recorded a small positive contribution of 0.29% from its share in associates, while HDFC reported no material contribution.
B21: Less: Minority Interest | C21: ='SBI IS'!D21/'SBI IS'!$D$7 -> 0.0060395911 | D21: ='SBI IS'!E21/'SBI IS'!$E$7 -> 0.006538497 | G21: Less: Minority Interest | H21: ='HDFC IS'!D20/'HDFC IS'!$D$7 -> 0.0078721058 | I21: ='HDFC IS'!E20/'HDFC IS'!$E$7 -> 0.0091605026 | K21: HDFC's minority interest deduction of 0.92% was higher than SBI's 0.65%, resulting in a greater reduction from consolidated profit.
B22: Net Profit | C22: ='SBI IS'!D22/'SBI IS'!$D$7 -> 0.15818749 | D22: ='SBI IS'!E22/'SBI IS'!$E$7 -> 0.16176639 | G22: Net Profit | H22: ='HDFC IS'!D21/'HDFC IS'!$D$7 -> 0.21046107 | I22: ='HDFC IS'!E21/'HDFC IS'!$E$7 -> 0.21807994 | K22: HDFC's net profit was 21.81% of interest earned versus SBI's 16.18%, indicating substantially stronger overall profitability relative to interest income.
B26: State Bank Of India | E26: VS | G26: HDFC Bank Limited
B28: Balance Sheet Growth Horizontal | G28: Balance Sheet Growth Horizontal
B29: INR ( Rupees in Crores) | G29: INR ( Rupees in Crores) | K29: HDFC has a more lending-oriented balance sheet with higher advances and liquidity balances,
B30: Line Items | C30: 2025 | D30: 2026 | G30: Line Items | H30: 2025 | I30: 2026 | K30: while SBI has greater exposure to investments and relies more heavily on deposits for funding.
B32: Capital and Liabilities | G32: Capital and Liabilities
B33: Capital | C33: ='SBI BS'!D8/'SBI BS'!$D$24 -> 0.00012201796 | D33: ='SBI BS'!E8/'SBI BS'!$E$24 -> 0.00011092402 | G33: Capital | H33: ='HDFC BS'!D8/'HDFC BS'!$D$24 -> 0.00017421386 | I33: ='HDFC BS'!E8/'HDFC BS'!$E$24 -> 0.00031363635 | K33: Both banks' capital represents a very small proportion of total assets, with HDFC marginally higher at 0.03% versus SBI at 0.01% in 2026.
B34: Reserves & Surplus | C34: ='SBI BS'!D9/'SBI BS'!$D$24 -> 0.066465953 | D34: ='SBI BS'!E9/'SBI BS'!$E$24 -> 0.071525915 | G34: Reserves & Surplus | H34: ='HDFC BS'!D9/'HDFC BS'!$D$24 -> 0.11775269 | I34: ='HDFC BS'!E9/'HDFC BS'!$E$24 -> 0.11816834 | K34: HDFC has a substantially higher reserves-to-assets ratio of 11.82% versus SBI's 7.15%, indicating a stronger relative equity reserve base.
B35: Minority Interest & Other Equity | C35: ='SBI BS'!D10/'SBI BS'!$D$24 -> 0.002464504 | D35: ='SBI BS'!E10/'SBI BS'!$E$24 -> 0.002255378 | G35: Minority Interest & Other Equity | H35: ='HDFC BS'!D10/'HDFC BS'!$D$24 -> 0.0045906907 | I35: ='HDFC BS'!E10/'HDFC BS'!$E$24 -> 0.0054869287 | K35: HDFC's ratio of 0.55% exceeds SBI's 0.23%, reflecting a greater contribution from minority and other equity interests.
B37: Deposits | C37: ='SBI BS'!D12/'SBI BS'!$D$24 -> 0.74374626 | D37: ='SBI BS'!E12/'SBI BS'!$E$24 -> 0.72619688 | G37: Deposits | H37: ='HDFC BS'!D12/'HDFC BS'!$D$24 -> 0.61717682 | I37: ='HDFC BS'!E12/'HDFC BS'!$E$24 -> 0.63154289 | K37: SBI has a higher deposit funding proportion at 72.62% versus HDFC's 63.15%, indicating greater reliance on deposits to fund assets.
B38: Borrowings | C38: ='SBI BS'!D13/'SBI BS'!$D$24 -> 0.083516785 | D38: ='SBI BS'!E13/'SBI BS'!$E$24 -> 0.093408128 | G38: Borrowings | H38: ='HDFC BS'!D13/'HDFC BS'!$D$24 -> 0.14447752 | I38: ='HDFC BS'!E13/'HDFC BS'!$E$24 -> 0.11990213 | K38: HDFC's borrowings represent 11.99% of assets versus SBI's 9.34%, indicating greater reliance on non-deposit funding.
B39: Other Liabilities and Provisions | C39: ='SBI BS'!D14/'SBI BS'!$D$24 -> 0.10368448 | D39: ='SBI BS'!E14/'SBI BS'!$E$24 -> 0.10650278 | G39: Other Liabilities and Provisions | H39: ='HDFC BS'!D14/'HDFC BS'!$D$24 -> 0.11582806 | I39: ='HDFC BS'!E14/'HDFC BS'!$E$24 -> 0.12458608 | K39: SBI's ratio of 10.65% is lower than HDFC's 12.46%, indicating a greater relative proportion of other liabilities and provisions at HDFC.
B40: Total Capital and Liabilities | C40: ='SBI BS'!D15/'SBI BS'!$D$24 -> 1 | D40: ='SBI BS'!E15/'SBI BS'!$E$24 -> 1 | G40: Total Capital and Liabilities | H40: ='HDFC BS'!D15/'HDFC BS'!$D$24 -> 1 | I40: ='HDFC BS'!E15/'HDFC BS'!$E$24 -> 1 | K40: Both banks equal 100%, as total liabilities and equity must equal total assets.
B42: Assets | G42: Assets
B43: Cash and Balances with Reserve Bank of India | C43: ='SBI BS'!D18/'SBI BS'!$D$24 -> 0.031101913 | D43: ='SBI BS'!E18/'SBI BS'!$E$24 -> 0.032287391 | G43: Cash and Balances with Reserve Bank of India | H43: ='HDFC BS'!D18/'HDFC BS'!$D$24 -> 0.032872616 | I43: ='HDFC BS'!E18/'HDFC BS'!$E$24 -> 0.040893529 | K43: HDFC holds a higher proportion of assets in cash/RBI balances at 4.09% versus SBI's 3.23%, indicating a relatively stronger liquidity position.
B44: Balances with Banks and Money at Call & Short Notice | C44: ='SBI BS'!D19/'SBI BS'!$D$24 -> 0.017834903 | D44: ='SBI BS'!E19/'SBI BS'!$E$24 -> 0.016001968 | G44: Balances with Banks and Money at Call & Short Notice | H44: ='HDFC BS'!D19/'HDFC BS'!$D$24 -> 0.024031789 | I44: ='HDFC BS'!E19/'HDFC BS'!$E$24 -> 0.022660557 | K44: HDFC's 2.27% is higher than SBI's 1.60%, indicating greater relative placement in interbank/liquid assets.
B45: Investments | C45: ='SBI BS'!D20/'SBI BS'!$D$24 -> 0.30155116 | D45: ='SBI BS'!E20/'SBI BS'!$E$24 -> 0.28354055 | G45: Investments | H45: ='HDFC BS'!D20/'HDFC BS'!$D$24 -> 0.27011843 | I45: ='HDFC BS'!E20/'HDFC BS'!$E$24 -> 0.26084059 | K45: SBI allocates 28.35% of assets to investments versus HDFC's 26.08%, indicating a greater investment allocation at SBI.
B46: Advances | C46: ='SBI BS'!D21/'SBI BS'!$D$24 -> 0.58117624 | D46: ='SBI BS'!E21/'SBI BS'!$E$24 -> 0.59820611 | G46: Advances | H46: ='HDFC BS'!D21/'HDFC BS'!$D$24 -> 0.62037322 | I46: ='HDFC BS'!E21/'HDFC BS'!$E$24 -> 0.6215888 | K46: HDFC has a higher advances-to-assets ratio of 62.16% versus SBI's 59.82%, indicating greater asset deployment toward lending.
B47: Fixed Assets | C47: ='SBI BS'!D22/'SBI BS'!$D$24 -> 0.0063353187 | D47: ='SBI BS'!E22/'SBI BS'!$E$24 -> 0.0068679481 | G47: Fixed Assets | H47: ='HDFC BS'!D22/'HDFC BS'!$D$24 -> 0.0034736999 | I47: ='HDFC BS'!E22/'HDFC BS'!$E$24 -> 0.0033601167 | K47: SBI's fixed assets represent 0.69% of assets versus HDFC's 0.34%, indicating a relatively higher fixed-asset allocation at SBI.
B48: Other Assets | C48: ='SBI BS'!D23/'SBI BS'!$D$24 -> 0.06200046 | D48: ='SBI BS'!E23/'SBI BS'!$E$24 -> 0.063096023 | G48: Other Assets | H48: ='HDFC BS'!D23/'HDFC BS'!$D$24 -> 0.049130242 | I48: ='HDFC BS'!E23/'HDFC BS'!$E$24 -> 0.0506564 | K48: SBI's other assets are 6.31% versus HDFC's 5.07%, indicating a slightly greater proportion of assets outside the major lending and investment categories.
B49: Total Assets | C49: ='SBI BS'!D24/'SBI BS'!$D$24 -> 1 | D49: ='SBI BS'!E24/'SBI BS'!$E$24 -> 1 | G49: Total Assets | H49: ='HDFC BS'!D24/'HDFC BS'!$D$24 -> 1 | I49: ='HDFC BS'!E24/'HDFC BS'!$E$24 -> 1 | K49: Base
B53: State Bank Of India | E53: VS | G53: HDFC Bank Limited
B55: Cash Flow Growth Horizontal | G55: Cash Flow Growth Horizontal
B56: INR ( Rupees in Crores) | G56: INR ( Rupees in Crores) | K56: HDFC generates substantially stronger operating cash relative to net profit, while
B57: Line Items | C57: 2025 | D57: 2026 | G57: Line Items | H57: 2025 | I57: 2026 | K57: investing and financing activities remain relatively small compared with total assets for both banks.
B59: Cash Flow From Operating Activites | G59: Cash Flow From Operating Activites
B60: Net Profit/(Loss) before taxes (including share in profit from associates and net of minority interest) | C60: ='SBI CF'!D8/'SBI IS'!D$22 -> 1.3526002 | D60: ='SBI CF'!E8/'SBI IS'!E$22 -> 1.3464578 | G60: Net Profit/(Loss) before taxes (including share in profit from associates and net of minority interest) | H60: ='HDFC CF'!D8/'HDFC IS'!D$21 -> 1.3220957 | I60: ='HDFC CF'!E8/'HDFC IS'!E$21 -> 1.3015021 | K60: SBI's PBT represents 134.65% of net profit versus HDFC's 130.15%, indicating a slightly higher pre-tax profit relative to final profit at SBI.
B61: Depreciation on Fixed Assets | C61: ='SBI CF'!D9/'SBI IS'!D$22 -> 0.051462196 | D61: ='SBI CF'!E9/'SBI IS'!E$22 -> 0.057980659 | G61: Depreciation on Fixed Assets | H61: ='HDFC CF'!D9/'HDFC IS'!D$21 -> 0.05375207 | I61: ='HDFC CF'!E9/'HDFC IS'!E$21 -> 0.055177198 | K61: SBI's depreciation is 5.80% versus HDFC's 5.52%, showing a marginally higher depreciation contribution at SBI.
B62: Other Operating Activities | C62: ='SBI CF'!D10/'SBI IS'!D$22 -> 0.26250386 | D62: ='SBI CF'!E10/'SBI IS'!E$22 -> 0.34686805 | G62: Other Operating Activities | H62: ='HDFC CF'!D10/'HDFC IS'!D$21 -> 0.28594655 | I62: ='HDFC CF'!E10/'HDFC IS'!E$21 -> 0.39989585 | K62: HDFC's other operating adjustments are 39.99% versus SBI's 34.69%, indicating a greater contribution from non-cash/other operating adjustments at HDFC.
B63: Tax refund / (Taxes paid) | C63: ='SBI CF'!D11/'SBI IS'!D$22 -> -0.43528705 | D63: ='SBI CF'!E11/'SBI IS'!E$22 -> -0.43605637 | G63: Tax refund / (Taxes paid) | H63: ='HDFC CF'!D11/'HDFC IS'!D$21 -> 0.41400521 | I63: ='HDFC CF'!E11/'HDFC IS'!E$21 -> -0.2980083 | K63: SBI's tax cash outflow is -43.61% versus HDFC's -29.80%, indicating a larger tax-related cash burden relative to profit for SBI.
B64: Change in Net Working Capital | C64: ='SBI CF'!D12/'SBI IS'!D$22 -> -0.64485287 | D64: ='SBI CF'!E12/'SBI IS'!E$22 -> -0.85789182 | G64: Change in Net Working Capital | H64: ='HDFC CF'!D12/'HDFC IS'!D$21 -> -0.27840166 | I64: ='HDFC CF'!E12/'HDFC IS'!E$21 -> 0.034427972 | K64: SBI's working-capital adjustment is -85.79%, while HDFC's is 3.44%, indicating significantly different working-capital effects on operating cash flow.
B66: Total Cash Flow From Operating Activites | C66: ='SBI CF'!D14/'SBI IS'!D$22 -> 0.58642631 | D66: ='SBI CF'!E14/'SBI IS'!E$22 -> 0.45735827 | G66: Total Cash Flow From Operating Activites | H66: ='HDFC CF'!D14/'HDFC IS'!D$21 -> 1.7973979 | I66: ='HDFC CF'!E14/'HDFC IS'!E$21 -> 1.4929948 | K66: HDFC generated CFO equivalent to 149.30% of net profit versus SBI's 45.74%, demonstrating substantially stronger cash conversion at HDFC.
B68: Cash Flow From Investing Activites | G68: Cash Flow From Investing Activites
B69: Purchase of Investments | C69: - | D69: - | G69: Purchase of Investments | H69: - | I69: - | K69: Neither bank shows a material percentage under this classification in the presented analysis.
B70: Sale Of Investments | C70: ='SBI CF'!D18/'SBI BS'!D$24 -> -8.9128176e-07 | D70: ='SBI CF'!E18/'SBI BS'!E$24 -> 0.0009348491 | G70: Sale Of Investments | H70: ='HDFC CF'!D18/'HDFC BS'!D$24 -> 4.3711693e-05 | I70: ='HDFC CF'!E18/'HDFC BS'!E$24 -> 0.0019979459 | K70: Both banks show a negligible contribution from sale of investments relative to total assets (SBI 0.09%, HDFC 0.20%).
B71: Purchase of Fixed Assets | C71: ='SBI CF'!D19/'SBI BS'!D$24 -> -0.00077072481 | D71: ='SBI CF'!E19/'SBI BS'!E$24 -> -0.0010049738 | G71: Purchase of Fixed Assets | H71: ='HDFC CF'!D19/'HDFC BS'!D$24 -> -0.00090500734 | I71: ='HDFC CF'!E19/'HDFC BS'!E$24 -> -0.00068508191 | K71: Both banks show a small negative contribution from fixed-asset purchases relative to total assets (SBI -0.10%, HDFC -0.07%), indicating limited capex intensity.
B72: Income from Investments in Associates | C72: ='SBI CF'!D20/'SBI BS'!D$24 -> 1.2306087e-06 | D72: ='SBI CF'!E20/'SBI BS'!E$24 -> 1.1174576e-07 | G72: Income from Investments in Associates | H72: ='HDFC CF'!D20/'HDFC BS'!D$24 -> -1.5360562e-05 | I72: ='HDFC CF'!E20/'HDFC BS'!E$24 -> -1.6477043e-05 | K72: The contribution is negligible for both banks relative to total assets, indicating limited cash-flow impact from this source.
B73: Total Cash Flow From Investing Activites | C73: ='SBI CF'!D21/'SBI BS'!D$24 -> -0.00077038548 | D73: ='SBI CF'!E21/'SBI BS'!E$24 -> -8.3023494e-05 | G73: Total Cash Flow From Investing Activites | H73: ='HDFC CF'!D21/'HDFC BS'!D$24 -> -0.00087665621 | I73: ='HDFC CF'!E21/'HDFC BS'!E$24 -> 0.0012963869 | K73: Investing cash flows represent a very small proportion of total assets for both banks (SBI -0.01%, HDFC 0.13%), indicating limited overall impact on their balance-sheet size.
B75: Cash Flow From Financing Activites | C75: ='SBI CF'!D23/'SBI BS'!D$24 -> 0 | D75: ='SBI CF'!E23/'SBI BS'!E$24 -> 0 | G75: Cash Flow From Financing Activites | H75: ='HDFC CF'!D23/'HDFC BS'!D$24 -> 0 | I75: ='HDFC CF'!E23/'HDFC BS'!E$24 -> 0
B76: Dividend paid | C76: ='SBI CF'!D24/'SBI BS'!D$24 -> -0.0016716446 | D76: ='SBI CF'!E24/'SBI BS'!E$24 -> -0.0017052249 | G76: Dividend paid | H76: ='HDFC CF'!D24/'HDFC BS'!D$24 -> -0.0033754055 | I76: ='HDFC CF'!E24/'HDFC BS'!E$24 -> -0.0042187872 | K76: Both banks show a small negative cash-flow contribution from dividends relative to total assets (SBI -0.17%, HDFC -0.42%), with HDFC's payout larger in relative terms.
B77: Other Financing Activities | C77: ='SBI CF'!D25/'SBI BS'!D$24 -> 0.00020370338 | D77: ='SBI CF'!E25/'SBI BS'!E$24 -> 0.001293387 | G77: Other Financing Activities | H77: ='HDFC CF'!D25/'HDFC BS'!D$24 -> -0.01995515 | I77: ='HDFC CF'!E25/'HDFC BS'!E$24 -> -0.0078032908 | K77: SBI's other financing activities were marginally positive (0.13% of total assets), while HDFC's were negative (-0.78%), reflecting a bigger net financing outflow at HDFC.
B78: Total Cash Flow From Financing Activites | C78: ='SBI CF'!D26/'SBI BS'!D$24 -> -0.0014679412 | D78: ='SBI CF'!E26/'SBI BS'!E$24 -> -0.00041183791 | G78: Total Cash Flow From Financing Activites | H78: ='HDFC CF'!D26/'HDFC BS'!D$24 -> -0.023330556 | I78: ='HDFC CF'!E26/'HDFC BS'!E$24 -> -0.012022078 | K78: Total financing cash flows were mildly negative for both banks, with HDFC's outflow (-1.20% of assets) considerably larger than SBI's (-0.04%).
B80: Effect of fluctuation in foreign currency translation reserve | C80: ='SBI CF'!D28/'SBI BS'!D$24 -> 0.00030737079 | D80: ='SBI CF'!E28/'SBI BS'!E$24 -> 0.0011933928 | G80: Effect of fluctuation in foreign currency translation reserve | H80: ='HDFC CF'!D28/'HDFC BS'!D$24 -> 4.5471544e-05 | I80: ='HDFC CF'!E28/'HDFC BS'!E$24 -> 0.0002269541 | K80: The foreign-currency translation effect is small for both banks (SBI 0.12%, HDFC 0.02% of total assets), indicating limited impact from currency adjustments.
B81: Net Change in Cash | C81: ='SBI CF'!D29/'SBI BS'!D$24 -> 0.0042876462 | D81: ='SBI CF'!E29/'SBI BS'!E$24 -> 0.0052766812 | G81: Net Change in Cash | H81: ='HDFC CF'!D29/'HDFC BS'!D$24 -> 0.0048067813 | I81: ='HDFC CF'!E29/'HDFC BS'!E$24 -> 0.01262788 | K81: Both banks show a positive net change in cash relative to total assets, with HDFC's increase (1.26%) more than double SBI's (0.53%).
B83: Cash and cash equivalents at the beginning of the year | C83: ='SBI CF'!D31/'SBI BS'!D$24 -> 0.04464917 | D83: ='SBI CF'!E31/'SBI BS'!E$24 -> 0.043012677 | G83: Cash and cash equivalents at the beginning of the year | H83: ='HDFC CF'!D31/'HDFC BS'!D$24 -> 0.052097624 | I83: ='HDFC CF'!E31/'HDFC BS'!E$24 -> 0.050926206 | K83: Beginning cash represents a broadly similar proportion of total assets for both banks (SBI 4.30%, HDFC 5.09%), indicating comparable starting liquidity relative to balance-sheet size.
B84: Cash and cash equivalents at the end of the year | C84: ='SBI CF'!D32/'SBI BS'!D$24 -> 0.048936816 | D84: ='SBI CF'!E32/'SBI BS'!E$24 -> 0.048289358 | G84: Cash and cash equivalents at the end of the year | H84: ='HDFC CF'!D32/'HDFC BS'!D$24 -> 0.056904405 | I84: ='HDFC CF'!E32/'HDFC BS'!E$24 -> 0.063554086 | K84: Ending cash represents a higher share of assets for HDFC (6.36%) than SBI (4.83%), indicating a relatively stronger year-end liquidity build at HDFC.

Sheet SBI DCF
B1: State Bank Of India
B3: DCF Valuation
B4: INR ( Rupees in Crores)
B7: Implied Share Price | C7: =C48 -> 1655.97
B8: Today's Share Price | C8: 1067.7
B10: Assumptions
B11: WACC | C11: =C50 -> 0.068073166
B12: TGR | C12: 0.04 | D12: Assumption: Terminal growth rate held below WACC and long-run risk-free rate; 4.0% used as a conservative long-run nominal growth proxy for a mature large-cap Indian bank.
B15: DCF | C15: 2024 | D15: 2025 | E15: 2026 | F15: 2027 | G15: 2028 | H15: 2029
B17: Revenue | C17: ='SBI IS Forecasting'!C$11 -> 334838.86 | D17: ='SBI IS Forecasting'!D$11 -> 362399.98 | E17: ='SBI IS Forecasting'!E$11 -> 397638.72 | F17: ='SBI IS Forecasting'!F$11 -> 433515.72 | G17: ='SBI IS Forecasting'!G$11 -> 472888.93 | H17: ='SBI IS Forecasting'!H$11 -> 516130.55
B18: % growth | D18: =(D17-C17)/C17 -> 0.082311611 | E18: =(E17-D17)/D17 -> 0.097237141 | F18: =(F17-E17)/E17 -> 0.090225104 | G18: =(G17-F17)/F17 -> 0.090823048 | H18: =(H17-G17)/G17 -> 0.09144139
B20: EBIT | C20: ='SBI IS Forecasting'!C14 -> 98945.018 | D20: ='SBI IS Forecasting'!D14 -> 125826.46 | E20: ='SBI IS Forecasting'!E14 -> 134988.27 | F20: ='SBI IS Forecasting'!F14 -> 156011.22 | G20: ='SBI IS Forecasting'!G14 -> 179690.32 | H20: ='SBI IS Forecasting'!H14 -> 206350.26
B21: % of Sales | C21: =C20/C17 -> 0.2955004 | D21: =D20/D17 -> 0.34720328 | E21: =E20/E17 -> 0.33947467 | F21: =F20/F17 -> 0.35987442 | G21: =G20/G17 -> 0.3799842 | H21: =H20/H17 -> 0.39980245
B23: Taxes | C23: ='SBI IS Forecasting'!C18 -> 23101.78 | D23: ='SBI IS Forecasting'!D18 -> 27348.14 | E23: ='SBI IS Forecasting'!E18 -> 28859.51 | F23: ='SBI IS Forecasting'!F18 -> 34456.402 | G23: ='SBI IS Forecasting'!G18 -> 39710.253 | H23: ='SBI IS Forecasting'!H18 -> 45609.048
B24: % of EBIT | C24: =C23/C20 -> 0.23348098 | D24: =D23/D20 -> 0.21734808 | E24: =E23/E20 -> 0.21379272 | F24: =F23/F20 -> 0.22085849 | G24: =G23/G20 -> 0.22099272 | H24: =H23/H20 -> 0.22102733
B26: EBIAT | C26: =C20-C23 -> 75843.238 | D26: =D20-D23 -> 98478.324 | E26: =E20-E23 -> 106128.76 | F26: =F20-F23 -> 121554.81 | G26: =G20-G23 -> 139980.07 | H26: =H20-H23 -> 160741.21
B28: Depreciation and Ammortization | C28: ='SBI CF Forecasting'!C9 -> 3849.1245 | D28: ='SBI CF Forecasting'!D9 -> 3991.4767 | E28: ='SBI CF Forecasting'!E9 -> 4829.7185 | F28: ='SBI CF Forecasting'!F9 -> 5426.1669 | G28: ='SBI CF Forecasting'!G9 -> 6096.2739 | H28: ='SBI CF Forecasting'!H9 -> 6849.1362
B29: % of Sales | C29: =C28/C17 -> 0.011495453 | D29: =D28/D17 -> 0.011014009 | E29: =E28/E17 -> 0.012145996 | F29: =F28/F17 -> 0.012516656 | G29: =G28/G17 -> 0.012891555 | H29: =H28/H17 -> 0.013270162
B31: CapEx | C31: ='SBI CF Forecasting'!C19 -> -4175.1262 | D31: ='SBI CF Forecasting'!D19 -> -5637.2241 | E31: ='SBI CF Forecasting'!E19 -> -8362.9582 | F31: ='SBI CF Forecasting'!F19 -> -8760.4981 | G31: ='SBI CF Forecasting'!G19 -> -9271.5975 | H31: ='SBI CF Forecasting'!H19 -> -9758.3235
B32: % of Sales | C32: =C31/C17 -> -0.012469061 | D32: =D31/D17 -> -0.015555255 | E32: =E31/E17 -> -0.021031549 | F32: =F31/F17 -> -0.020208029 | G32: =G31/G17 -> -0.01960629 | H32: =H31/H17 -> -0.018906696
B34: Change in NWC | C34: ='SBI CF Forecasting'!C12 -> -52223.064 | D34: ='SBI CF Forecasting'!D12 -> -50015.65 | E34: ='SBI CF Forecasting'!E12 -> -71461.347 | F34: ='SBI CF Forecasting'!F12 -> -75992.854 | G34: ='SBI CF Forecasting'!G12 -> -87177.369 | H34: ='SBI CF Forecasting'!H12 -> -100008
B35: % of sales | C35: =C34/C17 -> -0.15596477 | D35: =D34/D17 -> -0.13801229 | E35: =E34/E17 -> -0.17971426 | F35: =F34/F17 -> -0.17529435 | G35: =G34/G17 -> -0.18435062 | H35: =H34/H17 -> -0.19376494
B37: Unlevered FCF | C37: =C26+C28+C31+C34 -> 23294.172 | D37: =D26+D28+D31+D34 -> 46816.926 | E37: =E26+E28+E31+E34 -> 31134.175 | F37: =F26+F28+F31+F34 -> 42227.629 | G37: =G26+G28+G31+G34 -> 49627.377 | H37: =H26+H28+H31+H34 -> 57824.019
B38: Present Value of FCF | C38: =C37/(1+$C$50)^1 -> 21809.528 | D38: =D37/(1+$C$50)^1 -> 43833.07 | E38: =E37/(1+$C$50)^1 -> 29149.852 | F38: =F37/(1+$C$50)^1 -> 39536.27 | G38: =G37/(1+$C$50)^2 -> 43503.011 | H38: =H37/(1+$C$50)^3 -> 47457.545
B41: Terminal Value | C41: =H37*(1+$C$12)/($C$50-$C$12) -> 2142151.7
B42: Present Value of Terminal Value | C42: =C41/(1+$C$50)^3 -> 1758114.7
B43: Enterprise Value | C43: =SUM(F38:H38)+C42 -> 1888611.6 | D43: Enterprise Value = PV of explicit FY2027-2029 Unlevered FCF + PV of Terminal Value.
B44: Cash | C44: ='SBI BS Forecasting'!E18+'SBI BS Forecasting'!E19 -> 401843.21
B45: Debt | C45: =C52 -> 777302.15
B46: Equity Value | C46: =C43-C45+C44 -> 1513152.6
B47: Shares | C47: ='SBI IS Forecasting'!E27 -> 913.75608
B48: Share Price | C48: =C46/C47 -> 1655.97
B50: WACC | C50: =C53*C54*(1-C55)+C58*C59 -> 0.068073166 | D50: Comments
B52: Debt | C52: ='SBI BS Forecasting'!E13 -> 777302.15 | D52: Interest bearing borrowings excluding customer deposits
B53: % of Debt | C53: =C52/(C52+C57) -> 0.44132243 | D53: Debt/ (Debt + Equity Value)
B54: Cost Of Debt | C54: ='SBI IS Forecasting'!E8/('SBI BS Forecasting'!E12+'SBI BS Forecasting'!E13) -> 0.046185684 | D54: Total Interest Expense/ Deposit + Borrowings
B55: Tax Rate | C55: ='SBI IS Forecasting'!C36 -> 0.25446819
B57: Equity Value | C57: 984000 | D57: Taken the current equity value from the internet
B58: % of Equity | C58: =C57/(C52+C57) -> 0.55867757 | D58: Equity Value/ (Debt + Equity Value)
B59: Cost of Equity | C59: =C60+C61*C62 -> 0.094647 | D59: Risk Free Rate + Beta * Market Risk Premium
B60: Risk Free Rate | C60: 0.0676 | D60: India's 10 year G Sec yield (source: trading economics)
B61: Beta | C61: 0.37 | D61: SBI 5 year beta rate
B62: Market Risk Premium | C62: 0.0731 | D62: As per Aswath Damodaran's country premium update

Sheet HDFC DCF
B1: HDFC Bank Limited
B3: DCF Valuation
B4: INR ( Rupees in Crores)
B7: Implied Share Price | C7: =C47 -> 2112.1853
B8: Today's Share Price | C8: 727
B10: Assumptions
B11: WACC | C11: =C49 -> 0.068793733
B12: TGR | C12: 0.04 | D12: Assumption: Terminal growth rate held below WACC and long-run risk-free rate; 4.0% used as a conservative long-run nominal growth proxy for a mature large-cap Indian bank.
B15: DCF | C15: 2024 | D15: 2025 | E15: 2026 | F15: 2027 | G15: 2028 | H15: 2029
B17: Revenue | C17: ='HDFC IS Forecasting'!C$11 -> 253856.22 | D17: ='HDFC IS Forecasting'!D$11 -> 287021.73 | E17: ='HDFC IS Forecasting'!E$11 -> 309971.58 | F17: ='HDFC IS Forecasting'!F$11 -> 342741.6 | G17: ='HDFC IS Forecasting'!G$11 -> 379034.84 | H17: ='HDFC IS Forecasting'!H$11 -> 419235.29
B18: % growth | D18: =(D17-C17)/C17 -> 0.13064683 | E18: =(E17-D17)/D17 -> 0.07995858 | F18: =(F17-E17)/E17 -> 0.10571943 | G18: =(G17-F17)/F17 -> 0.10589098 | H18: =(H17-G17)/G17 -> 0.10606003
B20: EBIT | C20: ='HDFC IS Forecasting'!C14 -> 101586.88 | D20: ='HDFC IS Forecasting'!D14 -> 110416.66 | E20: ='HDFC IS Forecasting'!E14 -> 128797.67 | F20: ='HDFC IS Forecasting'!F14 -> 144746.54 | G20: ='HDFC IS Forecasting'!G14 -> 162656.86 | H20: ='HDFC IS Forecasting'!H14 -> 182767.62
B21: % of Sales | C21: =C20/C17 -> 0.40017487 | D21: =D20/D17 -> 0.38469791 | E21: =E20/E17 -> 0.41551445 | F21: =F20/F17 -> 0.42231972 | G21: =G20/G17 -> 0.42913433 | H21: =H20/H17 -> 0.43595477
B23: Taxes | C23: ='HDFC IS Forecasting'!C18 -> 10083.02 | D23: ='HDFC IS Forecasting'!D18 -> 21130.7 | E23: ='HDFC IS Forecasting'!E18 -> 20497.4 | F23: ='HDFC IS Forecasting'!F18 -> 21846.504 | G23: ='HDFC IS Forecasting'!G18 -> 24730.71 | H23: ='HDFC IS Forecasting'!H18 -> 27985.056
B24: % of EBIT | C24: =C23/C20 -> 0.09925514 | D24: =D23/D20 -> 0.19137239 | E24: =E23/E20 -> 0.15914418 | F24: =F23/F20 -> 0.15092938 | G24: =G23/G20 -> 0.15204222 | H24: =H23/H20 -> 0.15311823
B26: EBIAT | C26: =C20-C23 -> 91503.86 | D26: =D20-D23 -> 89285.96 | E26: =E20-E23 -> 108300.27 | F26: =F20-F23 -> 122900.03 | G26: =G20-G23 -> 137926.15 | H26: =H20-H23 -> 154782.57
B28: Depreciation and Ammortization | C28: ='HDFC CF Forecasting'!C9 -> 3092.08 | D28: ='HDFC CF Forecasting'!D9 -> 3805.23 | E28: ='HDFC CF Forecasting'!E9 -> 4194.9 | F28: ='HDFC CF Forecasting'!F9 -> 4893.4377 | G28: ='HDFC CF Forecasting'!G9 -> 5708.2965 | H28: ='HDFC CF Forecasting'!H9 -> 6658.8461
B29: % of Sales | C29: =C28/C17 -> 0.012180438 | D29: =D28/D17 -> 0.013257637 | E29: =E28/E17 -> 0.013533176 | F29: =F28/F17 -> 0.014277338 | G29: =G28/G17 -> 0.015060084 | H29: =H28/H17 -> 0.015883315
B31: CapEx | C31: ='HDFC CF Forecasting'!C19 -> -4186.9 | D31: ='HDFC CF Forecasting'!D19 -> -3975.17 | E31: ='HDFC CF Forecasting'!E19 -> -3362.41 | F31: ='HDFC CF Forecasting'!F19 -> -4417.8226 | G31: ='HDFC CF Forecasting'!G19 -> -16203.309 | H31: ='HDFC CF Forecasting'!H19 -> -17053.925
B32: % of Sales | C32: =C31/C17 -> -0.016493194 | D32: =D31/D17 -> -0.013849718 | E32: =E31/E17 -> -0.010847478 | F32: =F31/F17 -> -0.01288966 | G32: =G31/G17 -> -0.042748864 | H32: =H31/H17 -> -0.04067865
B34: Change in NWC | C34: ='HDFC CF Forecasting'!C12 -> -49706.22 | D34: ='HDFC CF Forecasting'!D12 -> -19708.68 | E34: ='HDFC CF Forecasting'!E12 -> 2617.42 | F34: ='HDFC CF Forecasting'!F12 -> -28476.546 | G34: ='HDFC CF Forecasting'!G12 -> -31026.279 | H34: ='HDFC CF Forecasting'!H12 -> -33804.309
B35: % of sales | C35: =C34/C17 -> -0.19580462 | D35: =D34/D17 -> -0.06866616 | E35: =E34/E17 -> 0.0084440645 | F35: =F34/F17 -> -0.083084593 | G35: =G34/G17 -> -0.081856007 | H35: =H34/H17 -> -0.080633262
B37: Unlevered FCF | C37: =C26+C28+C31+C34 -> 40702.82 | D37: =D26+D28+D31+D34 -> 69407.34 | E37: =E26+E28+E31+E34 -> 111750.18 | F37: =F26+F28+F31+F34 -> 94899.1 | G37: =G26+G28+G31+G34 -> 96404.861 | H37: =H26+H28+H31+H34 -> 110583.18
B38: Present Value of FCF | C38: =C37/(1+$C$49)^1 -> 38082.952 | D38: =D37/(1+$C$49)^1 -> 64939.883 | E38: =E37/(1+$C$49)^1 -> 104557.29 | F38: =F37/(1+$C$49)^1 -> 88790.846 | G38: =G37/(1+$C$49)^2 -> 84393.915 | H38: =H37/(1+$C$49)^3 -> 90574.799
B40: Terminal Value | C40: =H37*(1+$C$12)/($C$49-$C$12) -> 3994150.6
B41: Present Value of Terminal Value | C41: =C40/(1+$C$49)^3 -> 3271468.5
B42: Enterprise Value | C42: =SUM(F38:H38)+C41 -> 3535228.1 | D42: Enterprise Value = PV of explicit FY2027-2029 Unlevered FCF + PV of Terminal Value.
B43: Cash | C43: ='HDFC BS Forecasting'!E18+'HDFC BS Forecasting'!E19 -> 311926.05
B44: Debt | C44: =C51 -> 588484.55
B45: Equity Value | C45: =C42-C44+C43 -> 3258669.6
B46: Shares | C46: ='HDFC IS Forecasting'!E26 -> 1542.7953
B47: Share Price | C47: =C45/C46 -> 2112.1853
B49: WACC | C49: =C52*C53*(1-C54)+C57*C58 -> 0.068793733 | D49: Comments
B51: Debt | C51: ='HDFC BS Forecasting'!E13 -> 588484.55 | D51: Interest bearing borrowings excluding customer deposits
B52: % of Debt | C52: =C51/(C51+C56) -> 0.5137429 | D52: Debt/ (Debt + Equity Value)
B53: Cost Of Debt | C53: ='HDFC IS Forecasting'!E8/('HDFC BS Forecasting'!E12+'HDFC BS Forecasting'!E13) -> 0.050294211 | D53: Total Interest Expense/ Deposit + Borrowings
B54: Tax Rate | C54: ='HDFC IS Forecasting'!C36 -> 0.18749716
B56: Equity Value | C56: 557000 | D56: Taken the current equity value from the internet
B57: % of Equity | C57: =C56/(C51+C56) -> 0.4862571 | D57: Equity Value/ (Debt + Equity Value)
B58: Cost of Equity | C58: =C59+C60*C61 -> 0.098302 | D58: Risk Free Rate + Beta * Market Risk Premium
B59: Risk Free Rate | C59: 0.0676 | D59: India's 10 year G Sec yield (source: trading economics)
B60: Beta | C60: 0.42 | D60: SBI 5 year beta rate
B61: Market Risk Premium | C61: 0.0731 | D61: As per Aswath Damodaran's country premium update

Sheet SBI DDM
B1: State Bank Of India
B3: Dividend Discount Model (DDM) Valuation
B4: INR ( Rupees in Crores, except per-share data)
B7: Implied Share Price (DDM) | C7: =C29 -> 365.61775 | D7: PV of explicit FY2027-2029 dividends per share (row 25) + PV of Terminal Value (row 28)
B8: Today's Share Price | C8: ='SBI DCF'!C8 -> 1067.7
B9: Upside / (Downside) to Current Price | C9: =C7/C8-1 -> -0.65756509 | D9: DDM values SBI purely on the dividends it pays out (~16% of profit)
B10: Assumptions
B11: Cost of Equity (Ke) | C11: ='SBI DCF'!C59 -> 0.094647 | D11: Linked from 'SBI DCF'!C59 - same CAPM Cost of Equity (Risk-free rate + Beta x Equity Risk Premium)
B12: Terminal Growth Rate (g) | C12: ='SBI DCF'!C12 -> 0.04 | D12: 'SBI DCF'!C12 - same 4% long-run terminal growth assumption used for the FCFF DCF
B15: Dividend Build | C15: 2024 | D15: 2025 | E15: 2026 | F15: 2027 | G15: 2028 | H15: 2029
B17: Net Profit | C17: ='SBI IS Forecasting'!C22 -> 67084.663 | D17: ='SBI IS Forecasting'!D22 -> 77561.336 | E17: ='SBI IS Forecasting'!E22 -> 83298.786 | F17: ='SBI IS Forecasting'!F22 -> 98554.131 | G17: ='SBI IS Forecasting'!G22 -> 113324.9 | H17: ='SBI IS Forecasting'!H22 -> 129872.06
B18: Dividend Paid (Total) | C18: =-'SBI CF Forecasting'!C24 -> 10084.811 | D18: =-'SBI CF Forecasting'!D24 -> 12226.718 | E18: =-'SBI CF Forecasting'!E24 -> 14190.146 | F18: =-'SBI CF Forecasting'!F24 -> 15713.514 | G18: =-'SBI CF Forecasting'!G24 -> 18068.572 | H18: =-'SBI CF Forecasting'!H24 -> 20706.859
B19: Dividend Payout Ratio | C19: =C18/C17 -> 0.15032961 | D19: =D18/D17 -> 0.15763935 | E19: =E18/E17 -> 0.17035237 | F19: =F18/F17 -> 0.15944044 | G19: =G18/G17 -> 0.15944044 | H19: =H18/H17 -> 0.15944044
B20: Diluted Shares Outstanding (Cr) | C20: ='SBI IS Forecasting'!C27 -> 892.46119 | D20: ='SBI IS Forecasting'!D27 -> 892.46171 | E20: ='SBI IS Forecasting'!E27 -> 913.75608 | F20: ='SBI IS Forecasting'!F27 -> 924.65757 | G20: ='SBI IS Forecasting'!G27 -> 935.68913 | H20: ='SBI IS Forecasting'!H27 -> 946.85229
B21: Dividend Per Share (Rs) | C21: =C18/C20 -> 11.3 | D21: =D18/D20 -> 13.699992 | E21: =E18/E20 -> 15.529468 | F21: =F18/F20 -> 16.993874 | G21: =G18/G20 -> 19.310444 | H21: =H18/H20 -> 21.869155
B24: Present Value of Dividends (FY2027-2029)
B25: PV of DPS | F25: =F21/(1+$C$11)^1 -> 15.524524 | G25: =G21/(1+$C$11)^2 -> 16.115511 | H25: =H21/(1+$C$11)^3 -> 16.672845
B27: Terminal Value per Share | C27: =H21*(1+$C$12)/($C$11-$C$12) -> 416.19706 | D27: Gordon Growth terminal value: FY2029 DPS x (1+g) / (Ke-g)
B28: PV of Terminal Value per Share | C28: =C27/(1+$C$11)^3 -> 317.30487
B29: Intrinsic Value per Share (DDM) | C29: =SUM(F25:H25)+C28 -> 365.61775

Sheet HDFC DDM
B1: HDFC Bank Limited
B3: Dividend Discount Model (DDM) Valuation
B4: INR ( Rupees in Crores, except per-share data)
B7: Implied Share Price (DDM) | C7: =C29 -> 214.27549 | D7: PV of explicit FY2027-2029 dividends per share (row 25) + PV of Terminal Value
B8: Today's Share Price | C8: ='HDFC DCF'!C8 -> 727
B9: Upside / (Downside) to Current Price | C9: =C7/C8-1 -> -0.70526068 | D9: DDM values HDFC purely on the dividends it pays out (~20% of profit)
B10: Assumptions
B11: Cost of Equity (Ke) | C11: ='HDFC DCF'!C58 -> 0.098302 | D11: Linked from 'HDFC DCF'!C58 - same CAPM Cost of Equity (Risk-free rate + Beta x Equity Risk Premium)
B12: Terminal Growth Rate (g) | C12: ='HDFC DCF'!C12 -> 0.04 | D12: Linked from 'HDFC DCF'!C12 - same 4% long-run terminal growth assumption used for the FCFF DCF
B15: Dividend Build | C15: 2024 | D15: 2025 | E15: 2026 | F15: 2027 | G15: 2028 | H15: 2029
B17: Net Profit | C17: ='HDFC IS Forecasting'!C21 -> 64062.04 | D17: ='HDFC IS Forecasting'!D21 -> 70792.25 | E17: ='HDFC IS Forecasting'!E21 -> 76025.97 | F17: ='HDFC IS Forecasting'!F21 -> 91190.662 | G17: ='HDFC IS Forecasting'!G21 -> 103377.74 | H17: ='HDFC IS Forecasting'!H21 -> 117140.93
B18: Dividend Paid (Total) | C18: =-'HDFC CF Forecasting'!C24 -> 8404.42 | D18: =-'HDFC CF Forecasting'!D24 -> 14826.19 | E18: =-'HDFC CF Forecasting'!E24 -> 20705.98 | F18: =-'HDFC CF Forecasting'!F24 -> 18632.633 | G18: =-'HDFC CF Forecasting'!G24 -> 21122.772 | H18: =-'HDFC CF Forecasting'!H24 -> 23934.95
B19: Dividend Payout Ratio | C19: =C18/C17 -> 0.13119189 | D19: =D18/D17 -> 0.20943239 | E19: =E18/E17 -> 0.27235404 | F19: =F18/F17 -> 0.20432611 | G19: =G18/G17 -> 0.20432611 | H19: =H18/H17 -> 0.20432611
B20: Diluted Shares Outstanding (Cr) | C20: ='HDFC IS Forecasting'!C26 -> 1423.4427 | D20: ='HDFC IS Forecasting'!D26 -> 1532.3941 | E20: ='HDFC IS Forecasting'!E26 -> 1542.7953 | F20: ='HDFC IS Forecasting'!F26 -> 1607.2966 | G20: ='HDFC IS Forecasting'!G26 -> 1682.1805 | H20: ='HDFC IS Forecasting'!H26 -> 1760.5532
B21: Dividend Per Share (Rs) | C21: =C18/C20 -> 5.9042909 | D21: =D18/D20 -> 9.6751807 | E21: =E18/E20 -> 13.421081 | F21: =F18/F20 -> 11.592529 | G21: =G18/G20 -> 12.556781 | H21: =H18/H20 -> 13.59513
B24: Present Value of Dividends (FY2027-2029)
B25: PV of DPS | F25: =F21/(1+$C$11)^1 -> 10.554956 | G25: =G21/(1+$C$11)^2 -> 10.409617 | H25: =H21/(1+$C$11)^3 -> 10.26167
B27: Terminal Value per Share | C27: =H21*(1+$C$12)/($C$11-$C$12) -> 242.51202 | D27: Gordon Growth terminal value: FY2029 DPS x (1+g) / (Ke-g)
B28: PV of Terminal Value per Share | C28: =C27/(1+$C$11)^3 -> 183.04924
B29: Intrinsic Value per Share (DDM) | C29: =SUM(F25:H25)+C28 -> 214.27549

Sheet DDM Comparison
B1: SBI vs HDFC Bank — Valuation Comparison
B3: Dividend Discount Model (DDM) vs FCFF DCF
B4: INR ( Rupees in Crores, except per-share, ratio and % data)
B5: Metric | C5: SBI | D5: HDFC | E5: Comments
B6: Share Price Comparison
B7: Today's Share Price | C7: ='SBI DCF'!C8 -> 1067.7 | D7: ='HDFC DCF'!C8 -> 727 | E7: Actual NSE closing prices as of 14 Aug 2026, linked from each bank's DCF sheet.
B8: FCFF DCF Implied Share Price | C8: ='SBI DCF'!C7 -> 1655.97 | D8: ='HDFC DCF'!C7 -> 2112.1853 | E8: Unlevered free-cash-flow DCF result (see 'SBI DCF' / 'HDFC DCF' sheets); values 100% of cash the business generates, not just what is paid out.
B9: FCFF DCF Upside / (Downside) | C9: =C8/C7-1 -> 0.55096935 | D9: =D8/D7-1 -> 1.9053443 | E9: Both banks screen as undervalued on FCFF DCF, though the gap is sensitive to the WACC-vs-terminal-growth spread used in each model (see DCF sheet comments).
B10: DDM Implied Share Price | C10: ='SBI DDM'!C7 -> 365.61775 | D10: ='HDFC DDM'!C7 -> 214.27549 | E10: Dividend Discount Model result (see 'SBI DDM' / 'HDFC DDM' sheets); values only the dividend actually paid out to shareholders.
B11: DDM Upside / (Downside) | C11: ='SBI DDM'!C9 -> -0.65756509 | D11: ='HDFC DDM'!C9 -> -0.70526068 | E11: Both banks show a materially larger downside on DDM than on DCF - expected, since both retain the large majority of profit (see FY2026 payout ratios below: SBI ~17%, HDFC ~27%) to fund loan-book growth and capital ratios, and DDM does not credit that retained value.
B12: Average of DCF & DDM Implied Price | C12: =AVERAGE(C8,C10) -> 1010.7939 | D12: =AVERAGE(D8,D10) -> 1163.2304 | E12: A simple blend of the two methods; not a substitute for weighing which method's assumptions you trust more for each bank.
B14: DDM Assumptions & Drivers
B15: Cost of Equity (Ke) | C15: ='SBI DDM'!C11 -> 0.094647 | D15: ='HDFC DDM'!C11 -> 0.098302 | E15: CAPM-based cost of equity; HDFC's is slightly higher than SBI's because of its higher beta, despite both sharing the same risk-free rate and equity risk premium.
B16: Terminal Growth Rate (g) | C16: ='SBI DDM'!C12 -> 0.04 | D16: ='HDFC DDM'!C12 -> 0.04 | E16: Same 4.0% long-run growth assumption applied to both banks, for comparability.
B17: FY2026 Dividend Payout Ratio | C17: ='SBI DDM'!E19 -> 0.17035237 | D17: ='HDFC DDM'!E19 -> 0.27235404 | E17: HDFC pays out a larger share of profit as dividends than SBI, consistent with HDFC's stronger capital-adequacy cushion (see Ratio Analysis sheet).
B18: FY2026 Dividend Per Share (Rs) | C18: ='SBI DDM'!E21 -> 15.529468 | D18: ='HDFC DDM'!E21 -> 13.421081 | E18: Latest reported (FY2026) dividend per share for each bank.
B19: FY2029E Dividend Per Share (Rs) | C19: ='SBI DDM'!H21 -> 21.869155 | D19: ='HDFC DDM'!H21 -> 13.59513 | E19: Projected dividend per share at the end of the explicit forecast window, assuming the payout ratio stays at its FY2024-26 average.
B20: Terminal Value per Share (Rs) | C20: ='SBI DDM'!C27 -> 416.19706 | D20: ='HDFC DDM'!C27 -> 242.51202 | E20: Gordon Growth value of all dividends beyond FY2029, as of end-FY2029, before discounting back to today.
B21: PV of Terminal Value per Share (Rs) | C21: ='SBI DDM'!C28 -> 317.30487 | D21: ='HDFC DDM'!C28 -> 183.04924 | E21: Terminal value discounted back to today at each bank's cost of equity.
B22: PV of Explicit FY2027-29 Dividends (Rs) | C22: =SUM('SBI DDM'!F25:H25) -> 48.312881 | D22: =SUM('HDFC DDM'!F25:H25) -> 31.226244 | E22: Sum of the present value of the three explicitly forecast dividend payments; the terminal value (above) still dominates total DDM value for both banks.
B24: Interpretation
B25: DDM and FCFF DCF are not expected to agree for either bank: DDM only credits shareholders for cash actually distributed as dividends (SBI ~16% of profit, HDFC ~20%), while FCFF DCF credits 100% of cash generated, most of which these banks retain to fund loan-book growth and maintain regulatory capital ratios. For high-growth, low-payout banks like these, FCFF DCF (or an Excess Return / Residual Income model) is generally considered the more complete valuation approach; DDM is best read as a floor/conservative cross-check, not the primary estimate.
